Workbook

Sheet Welcome Page
C2: STATE UNIVERSAL BASIC EDUCATION BOARD | K2: Insert SUBEB logo here
C3: ANNUAL BASIC EDUCATION ACTION PLAN
B4: State (Select from the drop-down) | C4: BENUE
B5: Activities in this Action plan will be implemented in Year_ (Select from drop-down) | C5: 2025
B6: Action plan to be executed using Matching grants acccessed for year(s) (Specify the matching grant funding year(s) to finance this plan): (e.g 2024) | C6: 2025
B7: Action plan to be executed using Unconditional grants for year (Specify the unconditional grant funding year(s) to finance this plan): (e.g 2024) | C7: 2025 | FM7: Abia
B8: Total matching grant accessed (UBEC + State) (Insert amount in Nigerian Naira) | C8: 7.1092852e+09 | FM8: Adamawa
B9: Total unconditional grants accessed (Insert amount in Nigerian Naira)) | FM9: Adamawa
FM10: Akwa Ibom
B11: INSTRUCTIONS All action plan activities should be informed by the gaps and recommendations from the State's Rapid Assessment tool | CB11: Abia | CC11: 2025 | FM11: Anambra
B12: 1. Itemize and cost all infrastructure projects (construction, renovation, furniture etc.) - A summary of all infrastructure projects and their total costs filled here will appear in Tab: Pillar 1 - Access | FM12: Bauchi
B13: 2. Fill in other details under the applicable column headers under section "Priority 1.1." | CB13: Adamawa | CC13: 2026 | FM13: Bayelsa
B14: 3. Cost all other activities under tab Pillar 1- Access, ensuring each activity is properly organized under the appropriate priority initiatives (1.2 and 1.3) and other enablers sections | FM14: Benue
B15: 4. Develop and cost Sports development activities according to UBEC utilization guidelines - A summary of all Sports Development activities and costs will appear automatically in appropriate section in Tab: Pillar 2 - Quality | FM15: Borno
B16: 5. Outline and cost all Green School and Climate Change Initiative (GSCCI) activities across domains - A summary of all GSCCI activities and costs will appear automatically in the appropriate section in Tab: Pillar 2 - Quality | FM16: Cross River
B17: 6. Complete and cost all other activities under tab: Pillar 2 - Quality, ensuring each activity is properly organized under the appropriate Priority initiatives (2.1, 2.2, 2.3) and other Enablers sections | CB17: Ebonyi | FM17: Delta
B18: 7. Fill in other details under the applicabe column headers under sections "Sports Development" and "Green School and Climate Change Initiative (GSCCI)" in tab: Pillar 2 - Quality | FM18: Ebonyi
B19: 8. Complete and cost all activities under tab Pillar 3 -Systems Optimization, ensuring each activity is properly organized under the appropriate Priority initiatives (3.1, 3.2, 3.3 and 3.4) and the other Enablers sections | FM19: Edo
B20: 9. Conduct a resource mapping for all activities across UBE strategic pillars - ensuring alignment of all available funds across funding sources | CB20: Edo | FM20: Ekiti
CB21: Ekiti | FM21: Enugu
B22: Fill inputs in sheets in the following order below: | CB22: Enugu | FM22: Gombe
B23: Sheet name | C23: Description | CB23: FCT | FM23: Imo
B24: Welcome Page | C24: This is the landing sheet for this tool. It includes the description of sheets and instructions for completing this tool. Fill in the name of your state, action plan year and total matching grant accessed on this sheet Input IS REQUIRED on this sheet | CB24: Gombe | FM24: Jigawa
B25: Infrastructure Projects | C25: This sheet outlines all infrastructure projects planned for the year. It automatically populates the summary of these projects into Priority Initiative 1.1: Provide safe and adequate infrastructure for learning environments on Pillar 1 - Access sheet Outline and cost in all infrastructure projects (construction, renovation, water and sanitation, etc.) on this sheet Input IS REQUIRED on this sheet | FM25: Kaduna
B26: Pillar 1 - Access | C26: This sheet contains all activities aimed at improving access to basic education for the year, organized under the relevant priority initiatives and enablers Outline and cost all activities to improve access to basic education on this sheet Input IS REQUIRED on this sheet | CB26: Kaduna | FM26: Kano
B27: Sports Development | C27: This sheet provides a breakdown of all planned activities for the year across the four thematic utilization guideline areas of the Sports Development Fund. The summary of the entries in this sheet is automatically populated under the Sports Development sections on Pillar 2 - Quality sheet Outline and cost all sports activities on this sheet Input IS REQUIRED on this sheet | FM27: Katsina
B28: Green School and Climate Change and Safeguards (GSCCS) {NEW!} | C28: This sheet provides a breakdown of all planned Green School and Climate Change and Safeguarding activities for the year to enhance the quality of basic education, organized according to the six GSCCS pillars. The summary of inputs for each pillar is automatically populated under GSCCS section on Pillar 2 - Quality sheet. This is a newly revised matching grant domain which replaces AETP on previous template. Outline and cost all GSCCS activities on this sheet Input IS REQUIRED on this sheet | FM28: Kebbi
B29: Pillar 2 - Quality | C29: This sheet contains all activities planned for the year to enhance the quality of teaching and learning in basic education, organized under the relevant priority initiatives and enablers Outline and cost all activities to enhance quality of basic education on this sheet Input IS REQUIRED on this sheet | FM29: Kogi
B30: Pillar 3 - Systems Optimization | C30: This sheet contains all activities planned for the year to optimize basic education systems for quality service delivery, organized under the relevant priority initiatives and enablers Outline and cost all activities to optimize basic education systems on this sheet Input IS REQUIRED on this sheet | FM30: Kwara
B31: Total budget summary & Dashboard | C31: This sheet provides an overview of the budget for each pillar and funding source, as well as the distributions of matching grant formula across formula domains Input IS NOT REQUIRED on this sheet | CB31: Kebbi | FM31: Lagos
B32: DLIs (Disbursement linked indicators) and suggested activities (Project HOPE) | C32: This sheet maps the Project Hope-EDU Disbursement-Linked Indicators (DLIs) to BEAP Pillars, and also includes suggested activities to enabled the state achieve set milestones Input IS NOT REQUIRED on this sheet | CB32: Kwara | FM32: Nasarawa
CB33: Lagos | FM33: Niger
CB34: Nasarawa | FM34: Ogun
CB35: Niger | FM35: Ondo
CB36: Ogun | FM36: Osun
CB37: Ondo | FM37: Oyo
CB38: Osun | FM38: Plateau
CB39: Oyo | FM39: Rivers
CB40: Plateau | FM40: Sokoto
CB41: Rivers | FM41: Taraba
CB42: Sokoto | FM42: Yobe
CB43: Taraba | FM43: Zamfara
CB44: Yobe | FM44: FCT
CB45: Zamfara

Sheet Infrastructure Projects
B2: Click the rows below to go the infrastructure project type you would like to enter
B3: Construction: this includes all consturctions such as new schools, classroom blocks, perimeter fencing, toilets, ICT centres, laboratories, libraries, etc
B4: Renovation: this includes any renovation, upgrade or rehabilitation of an already established structure such as schools, classroom blocks, toilets, etc
B5: Furniture and equipment: this includes procurement of furniture such as desks, chairs, tables, shelves, etc and equipments such as generators, ICT equipments, etc
B6: Water Supply & Sanitation: this includes construction of water supply systems such as boreholes, taps, etc and waste disposal systems such as incinerators, etc
B7: Geophysical Survey: this includes details of the geophysical survey across the recommended locations for sinking of boreholes
B8: Teaching and Learning Materials (TLMs): this includes the list of beneficiary school for distribution of textbooks
I9: GRAND TOTAL INFRASTRUCTURE PROJECTS AND TLMs (No input required) | L9: =U13+U648+P957+P1266+P1421 -> 5.3319639e+09
U12: Total construction cost (No input required)
B13: Construction: this includes all NEW constructions such as new schools, classroom blocks, perimeter fencing, toilets, ICT centres, laboratories, libraries, etc | U13: =SUM(U15,U120,U225,U330,U436,P541) -> 1.2579713e+09
B15: Construction type: | D15: CONSTRUCTION OF UBE STANDARD BLOCK OF 3-CLASSROOMS, OFFICE, STORE AND 6NO. VENTILATED IMPROVED PIT TOILETS | U15: =SUM(T18:T118) -> 2.1905511e+08
B16: S/N | C16: Code | D16: Name of school | E16: LGA | F16: Quantity | G16: Component/Level of School | H16: Location Rural/Urban | I16: Justification for selecting the school (Rationale) | J16: Implementation strategy (Select from the drop-down list) | K16: GPS of school | M16: Duration of construction | N16: Expected output (Please specify quantity) | S16: Unit cost | T16: Total cost (No input required)
K17: Longitude | L17: Latitude | N17: No of classroms | O17: No of playrooms/Labs | P17: No of Libriaries | Q17: No of toilets | R17: No of offices/stores
B18: 1 | C18: UBEC/SUBEB/NC/001/2025 | D18: LGEA Primary School Wailomayo | E18: Makurdi | F18: 1 | G18: ECCDE | H18: Rural | I18: Expanding access to reduce overcrowding | J18: NCB | K18: 6.972923 | L18: 7.923681 | M18: 6 Months | N18: 3 | O18: 0 | P18: 0 | Q18: 6 | R18: 2 | S18: 1.0952756e+08 | T18: =F18*S18 -> 1.0952756e+08
B19: 2 | C19: UBEC/SUBEB/NC/002/2025 | D19: LGEA Primary School Atsor | E19: Gwer East | F19: 1 | G19: JSS | H19: Rural | I19: Expanding access to Basic Education inorder to bring back out-of-school children | J19: NCB | K19: 7.501173 | L19: 8.442443 | M19: 6 Months | N19: 3 | O19: 0 | P19: 0 | Q19: 6 | R19: 2 | S19: 1.0952756e+08 | T19: =F19*S19 -> 1.0952756e+08
B20: 3 | S20: 0 | T20: =F20*S20 -> 0
B21: 4 | S21: 0 | T21: =F21*S21 -> 0
B22: 5 | S22: 0 | T22: =F22*S22 -> 0
B23: 6 | S23: 0 | T23: =F23*S23 -> 0
B24: 7 | S24: 0 | T24: =F24*S24 -> 0
B25: 8 | S25: 0 | T25: =F25*S25 -> 0
B26: 9 | S26: 0 | T26: =F26*S26 -> 0
B27: 10 | S27: 0 | T27: =F27*S27 -> 0
B28: 11 | S28: 0 | T28: =F28*S28 -> 0
B29: 12 | S29: 0 | T29: =F29*S29 -> 0
B30: 13 | S30: 0 | T30: =F30*S30 -> 0
B31: 14 | S31: 0 | T31: =F31*S31 -> 0
... B117: 100 | S117: 0 | T117: =F117*S117 -> 0
D118: Insert new row as necessary above this line | S118: 0 | T118: =F118*S118 -> 0
B120: Construction type | D120: 3NO. BLOCKS OF TWIN COMPARTMENT VENTILATED IMPROVED PIT (VIP) TOILETS | U120: =SUM(T123:T223) -> 1.5171425e+08
B121: S/N | C121: Code | D121: Name of school | E121: LGA | F121: Quantity | G121: Component/Level of School | H121: Location Rural/Urban | I121: Justification for selecting the school (Rationale) | J121: Implementation strategy (Select from the drop-down list) | K121: GPS of school | M121: Duration | N121: Expected output (Please specify quantity) | S121: Unit cost | T121: Total cost (No input required)
K122: Longitude | L122: Latitude | N122: No of classroms | O122: No of playrooms/Labs | P122: No of Libriaries | Q122: No of toilets | R122: No of offices/stores
B123: 1 | C123: UBEC/SUBEB/WS/003/2025 | D123: LGEA Primary School Girgi | E123: Vadeikya | F123: 1 | G123: JSS | H123: Rural | I123: PROVIDE PROPER SANITORY ENVIRONMENT/ADEQUATE WASH FACILITY | J123: Request for quotation | K123: 6.813737 | L123: 9.043157 | M123: 3 MONTHS | N123: 0 | O123: 0 | P123: 0 | Q123: 6 | R123: 0 | S123: 25285708 | T123: =F123*S123 -> 25285708
B124: 2 | C124: UBEC/SUBEB/WS/004/2025 | D124: RCM Primary School Wajir Mbaave | E124: Ushongo | F124: 1 | G124: Primary | H124: Rural | I124: PROVIDE PROPER SANITORY ENVIRONMENT/ADEQUATE WASH FACILITY | J124: Request for quotation | K124: 7.082477 | L124: 9.017949 | M124: 3 MONTHS | N124: 0 | O124: 0 | P124: 0 | Q124: 6 | R124: 0 | S124: 25285708 | T124: =F124*S124 -> 25285708
B125: 3 | C125: UBEC/SUBEB/WS/005/2025 | D125: RCM Primary School Poor | E125: Makurdi | F125: 1 | G125: Primary | H125: Urban | I125: PROVIDE PROPER SANITORY ENVIRONMENT/ADEQUATE WASH FACILITY | J125: Request for quotation | K125: 7.707576 | L125: 8.532451 | M125: 3 MONTHS | N125: 0 | O125: 0 | P125: 0 | Q125: 6 | R125: 0 | S125: 25285708 | T125: =F125*S125 -> 25285708
B126: 4 | C126: UBEC/SUBEB/WS/006/2025 | D126: NKST Primary School Naka | E126: Gwer West | F126: 1 | G126: ECCDE | H126: Rural | I126: PROVIDE PROPER SANITORY ENVIRONMENT/ADEQUATE WASH FACILITY | J126: Request for quotation | K126: 7°34'34" | L126: 8°11'41" | M126: 3 MONTHS | N126: 0 | O126: 0 | P126: 0 | Q126: 6 | R126: 0 | S126: 25285708 | T126: =F126*S126 -> 25285708
B127: 5 | C127: UBEC/SUBEB/WS/007/2025 | D127: LGEA Primary School Ajide Ekeh | E127: Okpokwu | F127: 1 | G127: JSS | H127: Rural | I127: PROVIDE PROPER SANITORY ENVIRONMENT/ADEQUATE WASH FACILITY | J127: Request for quotation | K127: 7.01094 | L127: 7.85102 | M127: 3 MONTHS | N127: 0 | O127: 0 | P127: 0 | Q127: 6 | R127: 0 | S127: 25285708 | T127: =F127*S127 -> 25285708
B128: 6 | C128: UBEC/SUBEB/WS/008/2025 | D128: St Mary’s Pilot Primary School, Ogobia Ugboju | E128: Otukpo | F128: 1 | G128: ECCDE | H128: Urban | I128: PROVIDE PROPER SANITORY ENVIRONMENT/ADEQUATE WASH FACILITY | J128: Request for quotation | K128: 7.18991 | L128: 8.36891 | M128: 3 MONTHS | N128: 0 | O128: 0 | P128: 0 | Q128: 6 | R128: 0 | S128: 25285708 | T128: =F128*S128 -> 25285708
B129: 7 | S129: 0 | T129: =F129*S129 -> 0
B130: 8 | S130: 0 | T130: =F130*S130 -> 0
B131: 9 | S131: 0 | T131: =F131*S131 -> 0
B132: 10 | S132: 0 | T132: =F132*S132 -> 0
B133: 11 | S133: 0 | T133: =F133*S133 -> 0
B134: 12 | S134: 0 | T134: =F134*S134 -> 0
B135: 13 | S135: 0 | T135: =F135*S135 -> 0
B136: 14 | S136: 0 | T136: =F136*S136 -> 0
B137: 15 | S137: 0 | T137: =F137*S137 -> 0
B138: 16 | S138: 0 | T138: =F138*S138 -> 0
B139: 17 | S139: 0 | T139: =F139*S139 -> 0
B140: 18 | S140: 0 | T140: =F140*S140 -> 0
... B220: 98 | S220: 0 | T220: =F220*S220 -> 0
B221: 99 | T221: =F221*S221 -> 0
B222: 100 | T222: =F222*S222 -> 0
D223: Insert new row as necessary above this line | S223: 0 | T223: =F223*S223 -> 0
B225: Construction type: | U225: =SUM(T228:T328) -> 0
B226: S/N | C226: Code | D226: Name of school | E226: LGA | F226: Quantity | G226: Component/Level of School | H226: Location Rural/Urban | I226: Justification for selecting the school (Rationale) | J226: Implementation strategy (Select from the drop-down list) | K226: GPS of school | M226: Duration | N226: Expected output (Please specify quantity) | S226: Unit cost | T226: Total cost (No input required)
K227: Longitude | L227: Latitude | N227: No of classroms | O227: No of playrooms/Labs | P227: No of Libriaries | Q227: No of toilets | R227: No of offices/stores
B228: 1 | S228: 0 | T228: =F228*S228 -> 0
B229: 2 | S229: 0 | T229: =F229*S229 -> 0
B230: 3 | S230: 0 | T230: =F230*S230 -> 0
B231: 4 | S231: 0 | T231: =F231*S231 -> 0
B232: 5 | S232: 0 | T232: =F232*S232 -> 0
B233: 6 | S233: 0 | T233: =F233*S233 -> 0
B234: 7 | S234: 0 | T234: =F234*S234 -> 0
B235: 8 | S235: 0 | T235: =F235*S235 -> 0
B236: 9 | S236: 0 | T236: =F236*S236 -> 0
B237: 10 | S237: 0 | T237: =F237*S237 -> 0
B238: 11 | S238: 0 | T238: =F238*S238 -> 0
B239: 12 | S239: 0 | T239: =F239*S239 -> 0
... B327: 100 | S327: 0 | T327: =F327*S327 -> 0
D328: Insert new row as necessary above this line | S328: 0 | T328: =F328*S328 -> 0
B330: Construction type: | U330: =SUM(T333:T433) -> 0
B331: S/N | C331: Code | D331: Name of school | E331: LGA | F331: Quantity | G331: Component/Level of School | H331: Location Rural/Urban | I331: Justification for selecting the school (Rationale) | J331: Implementation strategy (Select from the drop-down list) | K331: GPS of school | M331: Duration | N331: Expected output (Please specify quantity) | S331: Unit cost | T331: Total cost (No input required)
K332: Longitude | L332: Latitude | N332: No of classroms | O332: No of playrooms/Labs | P332: No of Libriaries | Q332: No of toilets | R332: No of offices/stores
B333: 1 | S333: 0 | T333: =F333*S333 -> 0
B334: 2 | S334: 0 | T334: =F334*S334 -> 0
B335: 3 | S335: 0 | T335: =F335*S335 -> 0
B336: 4 | S336: 0 | T336: =F336*S336 -> 0
B337: 5 | S337: 0 | T337: =F337*S337 -> 0
B338: 6 | S338: 0 | T338: =F338*S338 -> 0
B339: 7 | S339: 0 | T339: =F339*S339 -> 0
B340: 8 | S340: 0 | T340: =F340*S340 -> 0
B341: 9 | S341: 0 | T341: =F341*S341 -> 0
B342: 10 | S342: 0 | T342: =F342*S342 -> 0
B343: 11 | S343: 0 | T343: =F343*S343 -> 0
B344: 12 | S344: 0 | T344: =F344*S344 -> 0
... B432: 100 | S432: 0 | T432: =F432*S432 -> 0
D433: Insert new row as necessary above this line | S433: 0 | T433: =F433*S433 -> 0
B436: Construction type: | U436: =SUM(T439:T539) -> 0
B437: S/N | C437: Code | D437: Name of school | E437: LGA | F437: Quantity | G437: Component/Level of School | H437: Location Rural/Urban | I437: Justification for selecting the school (Rationale) | J437: Implementation strategy (Select from the drop-down list) | K437: GPS of school | M437: Duration | N437: Expected output (Please specify quantity) | S437: Unit cost | T437: Total cost (No input required)
K438: Longitude | L438: Latitude | N438: No of classroms | O438: No of playrooms/Labs | P438: No of Libriaries | Q438: No of toilets | R438: No of offices/stores
B439: 1 | S439: 0 | T439: =F439*S439 -> 0
B440: 2 | S440: 0 | T440: =F440*S440 -> 0
B441: 3 | S441: 0 | T441: =F441*S441 -> 0
B442: 4 | S442: 0 | T442: =F442*S442 -> 0
B443: 5 | S443: 0 | T443: =F443*S443 -> 0
B444: 6 | S444: 0 | T444: =F444*S444 -> 0
B445: 7 | S445: 0 | T445: =F445*S445 -> 0
B446: 8 | S446: 0 | T446: =F446*S446 -> 0
B447: 9 | S447: 0 | T447: =F447*S447 -> 0
...

Sheet Description of sheets
B2: Sheet name | C2: Description
B3: Welcome Page | C3: This is the landing sheet for this tool. It includes the instructions for completing this tool. Fill in the name of your state and the action plan year on this sheet. INPUT IS REQUIRED ON THIS SHEET
B4: Description of sheets | C4: This sheet describes all the other sheets on this tool. NO INPUT REQUIRED ON THIS SHEET
B5: Unit Cost Set-Up | C5: This sheet includes all the unit costs required for costing activities. Update the sheet frequently with cost items and their unit costs. INPUT REQUIRED ON THIS SHEET
B6: Pillar 1,2,3 | C6: This sheet is where all the activities to be carried out in the year are listed, categorized under the relevant pillar and priority initiative. INPUT REQUIRED ON THIS SHEET
B7: Infrastructure Projects | C7: This sheet provides a break down of all infrastructure projects planned for the year. INPUT REQUIRED ON THIS SHEET
B8: Activity costing | C8: All activities listed under the Pillar 1,2,3 sheets should be costed here. INPUT REQUIRED ON THIS SHEET
B9: Total budget summary | C9: This sheet provides and overview of the budget for each pillar, the funding source and the funding gap. INPUT REQUIRED ON THIS SHEET
B10: Dashboard | C10: This sheet includes visualization the budget summary for each pillar and trackes the implementation status of activities. It is usefule during action plan review meetings NO INPUT REQUIRED ON THIS SHEET

Sheet Pillar 1 - Access
B2: Click to return to welcome page
B4: Pillar 1: Expand access to UBE especially for rural and underserved populations
H6: HOPE-DLI | I6: UBE Pillar
C7: Click to move to each sub-theme/sections
C8: Priority initiative 1.1: Provide safe and adequate infrastructure for learning environments
C9: Priority initiative 1.2: Expand enrollment of out-of-school children into the formal education system
C10: Priority initiative 1.3: Improve retention with incentives such as School-based management committee initiatives
C11: Enabler (Matching grant): Supervision and Project monitoring of ongoing infrastructure activities
C12: Enabler: Partnerships and cross-sector collaboration to expand access to basic education
C14: S/N | D14: Focus | E14: Activity (No input is required/autogenerated from infrastructure projects) | F14: Total quantity required (from needs assessment) | G14: Total quantity planned (No input required) | H14: Target group (Select from the drop-down) | I14: Number of expected beneficiaries | J14: Expected output/Deliverable | K14: Timeline/Duration | L14: Expected start date MM-DD-YYYY | M14: Expected due date MM-DD-YYYY | N14: Achievement indicator (% of project completed) | O14: Total cost (No input required) | P14: Implementation strategy (Select from the drop-down list) | Q14: Resource mapping | X14: Infrastructure Gap (No input required) | Y14: Funding gap (No input required) | Z14: Remarks
Q15: Government fund | T15: Development partner 1 | V15: Development partner 2
Q16: State Government education budget | R16: UBEC+State matching grant | S16: Unconditional grants/Emergency funds | T16: Name | U16: Amount | V16: Name | W16: Amount
C17: Priority initiative 1.1: Provide safe and adequate infrastructure for learning environments (Hope-EDU DLI)
C18: Objective: To enhance access to education for children in a conducive, safe and modern environment to enhance effective teaching, learning and administration
C19: 1.1.1 | D19: Construction | E19: ='Infrastructure Projects'!D15 -> CONSTRUCTION OF UBE STANDARD BLOCK OF 3-CLASSROOMS, OFFICE, STORE AND 6NO. VENTILATED IMPROVED PIT TOILETS | F19: 2401 | G19: =SUM('Infrastructure Projects'!F18:F118) -> 2 | H19: Primary School Learners and Teachers | I19: 240 | J19: 6 Classrooms, 2 Offices, 2 Stores and 12 Toilets will be delivered | K19: 6 Months | L19: 45962 | M19: 46053 | N19: 100% Project completion | O19: ='Infrastructure Projects'!U15 -> 2.1905511e+08 | P19: NCB | Q19: 0 | R19: 2.1905511e+08 | S19: 0 | U19: 0 | W19: 0 | X19: =(F19-G19) -> 2399 | Y19: =O19-(Q19+R19+S19+U19+W19) -> 0
C20: 1.1.2 | E20: ='Infrastructure Projects'!D120 -> 3NO. BLOCKS OF TWIN COMPARTMENT VENTILATED IMPROVED PIT (VIP) TOILETS | F20: 397 | G20: =SUM('Infrastructure Projects'!F123:F223) -> 6 | H20: Primary School Learners and Teachers | I20: 2732 | J20: 36 Toilets will be delivered | K20: 6 Months | L20: 45962 | M20: 46053 | N20: 100% Project completion | O20: ='Infrastructure Projects'!U120 -> 1.5171425e+08 | P20: Request for quotation | Q20: 0 | R20: 1.5171425e+08 | S20: 0 | U20: 0 | W20: 0 | X20: =(F20-G20) -> 391 | Y20: =O20-(Q20+R20+S20+U20+W20) -> 0
C21: 1.1.3 | E21: ='Infrastructure Projects'!D225 -> 0 | G21: =SUM('Infrastructure Projects'!F228:F328) -> 0 | J21: 6 Classrooms, 2 Offices, 2 Stores and 12 Toilets will be delivered | M21: 46053 | O21: ='Infrastructure Projects'!U225 -> 0 | Q21: 0 | R21: 0 | S21: 0 | U21: 0 | W21: 0 | X21: =(F21-G21) -> 0 | Y21: =O21-(Q21+R21+S21+U21+W21) -> 0
C22: 1.1.4 | E22: ='Infrastructure Projects'!D330 -> 0 | G22: =SUM('Infrastructure Projects'!F333:F433) -> 0 | J22: 6 Classrooms, 2 Offices, 2 Stores and 12 Toilets will be delivered | M22: 46053 | O22: ='Infrastructure Projects'!U330 -> 0 | Q22: 0 | R22: 0 | S22: 0 | U22: 0 | W22: 0 | X22: =(F22-G22) -> 0 | Y22: =O22-(Q22+R22+S22+U22+W22) -> 0
C23: 1.1.5 | E23: ='Infrastructure Projects'!D436 -> 0 | G23: =SUM('Infrastructure Projects'!F439:F539) -> 0 | J23: 6 Classrooms, 2 Offices, 2 Stores and 12 Toilets will be delivered | M23: 46053 | O23: ='Infrastructure Projects'!U436 -> 0 | Q23: 0 | R23: 0 | S23: 0 | U23: 0 | W23: 0 | X23: =(F23-G23) -> 0 | Y23: =O23-(Q23+R23+S23+U23+W23) -> 0
C24: 1.1.6 | E24: ='Infrastructure Projects'!D541 -> CONSTRUCTION OF PERIMETER FENCE AND GATE HOUSE | F24: 3920400 | G24: =SUM('Infrastructure Projects'!F544:F644) -> 5756 | H24: All Learners and Teachers | I24: 3212 | J24: 5,171M perimeter fences, 8 Gatehouses, external works, 8 Toilets, Purpose made steel Metal grille and galvanised razoor fence Concertina wire will be delivered | K24: 6 Months | L24: 45962 | M24: 46053 | N24: 100% Project completion | O24: ='Infrastructure Projects'!P541 -> 8.8720192e+08 | P24: NCB | Q24: 0 | R24: 8.0945803e+08 | S24: 0 | U24: 0 | W24: 0 | X24: =(F24-G24) -> 3914644 | Y24: =O24-(Q24+R24+S24+U24+W24) -> 77743891 | Z24: THE NUMBER OF PERIMETER FENCE IS IN METERS SO ITS DIFFICULT TO ESTIMATE
C25: 1.1.7 | D25: Renovation | E25: ='Infrastructure Projects'!D649 -> Reha/Renovation of Classrooms, Offices, Stores, Libraries and Toilets (Whole School Approach). | F25: 502 | G25: =SUM('Infrastructure Projects'!F652:F762) -> 9 | H25: All Learners and Teachers | I25: 3280 | J25: 79 Classrooms, 3 Playrooms, 1 Library, 13 Offices, 13 Stores and 24 Toilets will be delivered | K25: 6 Months | L25: 45962 | M25: 46053 | N25: 100% Project completion | O25: ='Infrastructure Projects'!U649 -> 1.2463821e+09 | P25: NCB | Q25: 0 | R25: 1.2463821e+09 | S25: 0 | U25: 0 | W25: 0 | X25: =(F25-G25) -> 493 | Y25: =O25-(Q25+R25+S25+U25+W25) -> 0
C26: 1.1.8 | D26: Furniture and equipment | E26: ='Infrastructure Projects'!D958 -> EQUIPMENT; COMPUTERS IN DIGITAL LIBRARIES, FURNITURE; CONSTRUCTION OF 2-SEATER DUAL-DESK OF STEEL/WOOD | F26: 335760 | G26: =SUM('Infrastructure Projects'!F961:F1261) -> 3115 | H26: All Learners and Teachers | I26: 6572 | J26: 3,286No. equipment; computers in digital libraries, furniture; fabricated 2-seater dual-desk of steel/wood will be delivered | K26: 3 Months | L26: 45962 | M26: 46053 | N26: 100% Project completion | O26: ='Infrastructure Projects'!P958 -> 1.8503095e+09 | P26: NCB | Q26: 0 | R26: 1.9272794e+09 | S26: 0 | U26: 0 | W26: 0 | X26: =(F26-G26) -> 332645 | Y26: =O26-(Q26+R26+S26+U26+W26) -> -76969891
C27: 1.1.9 | D27: Water Supply & Sanitation (including Geophysical survey) | E27: ='Infrastructure Projects'!D1267 -> DRILLING OF MOTORIZED BOREHOLES WITH OVERHEAD STEEL STANCTION, 4000L PVC TANK AND INSTALLATION OF SOLAR RACK/PUMPS | F27: 3268 | G27: ='Infrastructure Projects'!P1266 -> 255675000 | H27: All Learners and Teachers | I27: 4282 | J27: 10 motorized boreholes with overhead steel stanction, 4000l pvc tank and installation of solar rack/pumps will be delivered | K27: 3 Months | L27: 45962 | M27: 46053 | N27: 100% Project completion | O27: ='Infrastructure Projects'!P1267 -> 254000000 | P27: Request for quotation | Q27: 0 | R27: 250000000 | S27: 0 | U27: 0 | W27: 0 | X27: =(F27-G27) -> -255671732 | Y27: =O27-(Q27+R27+S27+U27+W27) -> 4000000
D28: TOTAL | O28: =SUM(O19:O27) -> 4.6086629e+09 | Q28: =SUM(Q19:Q27) -> 0 | R28: =SUM(R19:R27) -> 4.6038889e+09 | S28: =SUM(S19:S27) -> 0 | T28: =SUM(U19:U27,W19:W27) -> 0 | Y28: =SUM(Y19:Y27) -> 4774000
C30: S/N | D30: Activity | E30: Rationale/Reason for choice of activity | F30: Quantity | G30: Expected output | H30: Number of expected beneficiaries (OOSC) | I30: Target group (Select from the drop-down) | J30: Timeline (Shade as applicable) | N30: Expected due date MM-DD-YYYY | O30: Achievement indicator (% of project completed) | P30: Unit cost | Q30: Total cost (No input required) | R30: Implementation strategy (Select from the drop-down list) | S30: Resource mapping | Z30: Funding gap (No input required) | AA30: Remarks
S31: Government fund | V31: Development partner 1 | X31: Development partner 2
J32: Q1 | K32: Q2 | L32: Q3 | M32: Q4 | S32: State Government education budget | T32: UBEC matching grant | U32: Unconditional grants/Emergency funds | V32: Name | W32: Amount | X32: Name | Y32: Amount | Z32: (No input required)
C33: Priority initiative 1.2: Expand enrollment of out-of-school children into the formal education system (Hope-EDU DLI)
C34: Objective: Reintegrate out of school children and increase enrolment to improve access to education
C35: 1.2.Ex | D35: Implement open school activities in nomadic and high density IDP camps across 3 LGAs | E35: High number of OOSC children due to conflict | F35: 9 | G35: 9 Informal schools established across 9 IDP camps | H35: 540 OOSC children reintegrated | I35: Primary School Learners | N35: 05-21-2025 | O35: 100% of informal schools established in selected IDP camps | Q35: =F35*P35 -> 0 | S35: 0 | V35: UNICEF | Y35: 0 | Z35: =Q35-(S35+T35+U35+W35+Y35) -> 0
C36: 1.2.1 | P36: 0 | Q36: =F36*P36 -> 0 | S36: 0 | T36: 0 | U36: 0 | W36: 0 | Y36: 0 | Z36: =Q36-(S36+T36+U36+W36+Y36) -> 0
C37: 1.2.2 | P37: 0 | Q37: =F37*P37 -> 0 | S37: 0 | T37: 0 | U37: 0 | W37: 0 | Y37: 0 | Z37: =Q37-(S37+T37+U37+W37+Y37) -> 0
C38: 1.2.3 | P38: 0 | Q38: =F38*P38 -> 0 | S38: 0 | T38: 0 | U38: 0 | W38: 0 | Y38: 0 | Z38: =Q38-(S38+T38+U38+W38+Y38) -> 0
C39: 1.2.4 | P39: 0 | Q39: =F39*P39 -> 0 | S39: 0 | T39: 0 | U39: 0 | W39: 0 | Y39: 0 | Z39: =Q39-(S39+T39+U39+W39+Y39) -> 0
C40: 1.2.5 | P40: 0 | Q40: =F40*P40 -> 0 | S40: 0 | T40: 0 | U40: 0 | W40: 0 | Y40: 0 | Z40: =Q40-(S40+T40+U40+W40+Y40) -> 0
C41: 1.2.6 | P41: 0 | Q41: =F41*P41 -> 0 | S41: 0 | T41: 0 | U41: 0 | W41: 0 | Y41: 0 | Z41: =Q41-(S41+T41+U41+W41+Y41) -> 0
C42: 1.2.7 | P42: 0 | Q42: =F42*P42 -> 0 | S42: 0 | T42: 0 | U42: 0 | W42: 0 | Y42: 0 | Z42: =Q42-(S42+T42+U42+W42+Y42) -> 0
C43: 1.2.8 | P43: 0 | Q43: =F43*P43 -> 0 | S43: 0 | T43: 0 | U43: 0 | W43: 0 | Y43: 0 | Z43: =Q43-(S43+T43+U43+W43+Y43) -> 0
C44: 1.2.9 | P44: 0 | Q44: =F44*P44 -> 0 | S44: 0 | T44: 0 | U44: 0 | W44: 0 | Y44: 0 | Z44: =Q44-(S44+T44+U44+W44+Y44) -> 0
C45: 1.2.10 | P45: 0 | Q45: =F45*P45 -> 0 | S45: 0 | T45: 0 | U45: 0 | W45: 0 | Y45: 0 | Z45: =Q45-(S45+T45+U45+W45+Y45) -> 0
C46: 1.2.11 | P46: 0 | Q46: =F46*P46 -> 0 | S46: 0 | T46: 0 | U46: 0 | W46: 0 | Y46: 0 | Z46: =Q46-(S46+T46+U46+W46+Y46) -> 0
C47: 1.2.12 | P47: 0 | Q47: =F47*P47 -> 0 | S47: 0 | T47: 0 | U47: 0 | W47: 0 | Y47: 0 | Z47: =Q47-(S47+T47+U47+W47+Y47) -> 0
... C65: 1.2.30 | P65: 0 | Q65: =F65*P65 -> 0 | S65: 0 | T65: 0 | U65: 0 | W65: 0 | Y65: 0 | Z65: =Q65-(S65+T65+U65+W65+Y65) -> 0
C66: Total | Q66: =SUM(Q35:Q65) -> 0 | S66: =SUM(S35:S65) -> 0 | T66: =SUM(T35:T65) -> 0 | U66: =SUM(U35:U65) -> 0 | V66: =SUM(W35:W65,Y35:Y65) -> 0 | Z66: =SUM(Z35:Z65) -> 0
C68: S/N | D68: Activity | E68: Rationale/Reason for choice of activity | F68: Quantity | G68: Expected output | H68: Number of expected beneficiaries (OOSC) | I68: Target group (Select from the drop-down) | J68: Timeline (Shade as applicable) | N68: Expected due date MM-DD-YYYY | O68: Achievement indicator (% of project completed) | P68: Unit cost | Q68: Total cost (No input required) | R68: Implementation strategy (Select from the drop-down list) | S68: Resource mapping | Z68: Funding gap | AA68: Remarks
S69: Government fund | V69: Development partner 1 | X69: Development partner 2
J70: Q1 | K70: Q2 | L70: Q3 | M70: Q4 | S70: State Government education budget | T70: UBEC matching grant | U70: Unconditional grants/Emergency funds | V70: Name | W70: Amount | X70: Name | Y70: Amount | Z70: (No input required)
C71: Priority initiative 1.3 (Matching grant): Improve retention with incentives such as School Based Management Committee (SMBC) initiatives
C72: Objective: Attract and retain learners through advocacy, behavior change, and demand generation, including for girls and learners with special needs
C73: 1.3.1 | D73: Capacity Building and Training SBMC members on roles, responsibilities, school development planning, financial management, and monitoring in 3 Senatorial Zones ( SBMC Chairman, LGEA Desk Officers, Head Teachers and SUBEB SBMC Desk 250 per zone) 3 days, feeding, materials, Resource persons,transportation and venue | E73: To strengthen school-based governance, accountability, and community participation in the delivery of quality basic education, ensuring equity, inclusion, and effective decision-making. | F73: 750 | G73: 750 SBMC members and school administrators trained on increased collaboration in communities. | H73: NA | I73: All Learners and Teachers | N73: 46142 | O73: 100% Completion | P73: 102000 | Q73: =F73*P73 -> 76500000 | S73: 0 | T73: 76500000 | U73: 0 | W73: 0 | Y73: 0 | Z73: =Q73-(S73+T73+U73+W73+Y73) -> 0
C74: 1.3.2 | D74: Procurement of Pickup Hilux Van 2025 model | E74: To facilitate monitoring of SBMC activities and the implementation SBMC projects across the 23 LGAs | F74: 1 | G74: 1No Hilux Van acquired | H74: NA | I74: All Learners and Teachers | N74: 46142 | O74: 100% acquisition of utility van | P74: 1.4977922e+08 | Q74: =F74*P74 -> 1.4977922e+08 | S74: 0 | T74: 1.4977922e+08 | U74: 0 | W74: 0 | Y74: 0 | Z74: =Q74-(S74+T74+U74+W74+Y74) -> 0 | AA74: The price covers taxes and delivery services
C75: 1.3.3 | D75: Develop - state-wide behavioural change enrollment drive campaign in three zones | E75: To cut down number of out of school children | F75: 3 | G75: Enrolment and retention drive in the 3 senatorial district | H75: 1200 | I75: All Learners and Teachers | N75: 46142 | O75: Different outreaches | P75: 16452992 | Q75: =F75*P75 -> 49358976 | S75: 0 | T75: 49358976 | U75: 0 | W75: 0 | Y75: 0 | Z75: =Q75-(S75+T75+U75+W75+Y75) -> 0
C76: 1.3.4 | D76: Fueling/Maintenance of Hilux Van @N170,000.00 per day (5 visit per LGA) | E76: To facilitate easy mobility | F76: 115 | G76: 115 movements will be achieved | H76: NA | I76: All Learners and Teachers | N76: 46142 | O76: 100% Fueling/maintenance of utility van | P76: 170000 | Q76: =F76*P76 -> 19550000 | S76: 0 | T76: 19550000 | U76: 0 | W76: 0 | Y76: 0 | Z76: =Q76-(S76+T76+U76+W76+Y76) -> 0 | AA76: The 5 visits to each LGA covers monitoring of renovation projects at 1-commencement, 2-roof level, 3-finishes, 4-handover and 5-other SBMC activities.
C77: 1.3.5 | P77: 0 | Q77: =F77*P77 -> 0 | S77: 0 | T77: 0 | U77: 0 | W77: 0 | Y77: 0 | Z77: =Q77-(S77+T77+U77+W77+Y77) -> 0
C78: 1.3.6 | P78: 0 | Q78: =F78*P78 -> 0 | S78: 0 | T78: 0 | U78: 0 | W78: 0 | Y78: 0 | Z78: =Q78-(S78+T78+U78+W78+Y78) -> 0
C79: 1.3.7 | P79: 0 | Q79: =F79*P79 -> 0 | S79: 0 | T79: 0 | U79: 0 | W79: 0 | Y79: 0 | Z79: =Q79-(S79+T79+U79+W79+Y79) -> 0
C80: 1.3.8 | P80: 0 | Q80: =F80*P80 -> 0 | S80: 0 | T80: 0 | U80: 0 | W80: 0 | Y80: 0 | Z80: =Q80-(S80+T80+U80+W80+Y80) -> 0
C81: 1.3.9 | P81: 0 | Q81: =F81*P81 -> 0 | S81: 0 | T81: 0 | U81: 0 | W81: 0 | Y81: 0 | Z81: =Q81-(S81+T81+U81+W81+Y81) -> 0
C82: 1.3.10 | P82: 0 | Q82: =F82*P82 -> 0 | S82: 0 | T82: 0 | U82: 0 | W82: 0 | Y82: 0 | Z82: =Q82-(S82+T82+U82+W82+Y82) -> 0
C83: 1.3.11 | P83: 0 | Q83: =F83*P83 -> 0 | S83: 0 | T83: 0 | U83: 0 | W83: 0 | Y83: 0 | Z83: =Q83-(S83+T83+U83+W83+Y83) -> 0
C84: 1.3.12 | P84: 0 | Q84: =F84*P84 -> 0 | S84: 0 | T84: 0 | U84: 0 | W84: 0 | Y84: 0 | Z84: =Q84-(S84+T84+U84+W84+Y84) -> 0
C85: 1.3.13 | P85: 0 | Q85: =F85*P85 -> 0 | S85: 0 | T85: 0 | U85: 0 | W85: 0 | Y85: 0 | Z85: =Q85-(S85+T85+U85+W85+Y85) -> 0
C86: 1.3.14 | P86: 0 | Q86: =F86*P86 -> 0 | S86: 0 | T86: 0 | U86: 0 | W86: 0 | Y86: 0 | Z86: =Q86-(S86+T86+U86+W86+Y86) -> 0
C87: 1.3.15 | P87: 0 | Q87: =F87*P87 -> 0 | S87: 0 | T87: 0 | U87: 0 | W87: 0 | Y87: 0 | Z87: =Q87-(S87+T87+U87+W87+Y87) -> 0
C88: 1.3.16 | P88: 0 | Q88: =F88*P88 -> 0 | S88: 0 | T88: 0 | U88: 0 | W88: 0 | Y88: 0 | Z88: =Q88-(S88+T88+U88+W88+Y88) -> 0
... C117: 1.3.45 | P117: 0 | Q117: =F117*P117 -> 0 | S117: 0 | T117: 0 | U117: 0 | W117: 0 | Y117: 0 | Z117: =Q117-(S117+T117+U117+W117+Y117) -> 0
C118: 1.3.46 | D118: Supervision/Enforcement of funds distribution and utilization | E118: To effectively monitor the funds disbursed | F118: 23 | G118: 3,000number of supervision will be covered | H118: NA | I118: Teachers | N118: 46142 | O118: 100% effective monitoring of the 3,000no of schools will be achieved | Q118: =F118*P118 -> 0 | S118: 0 | T118: 0 | U118: 8500000 | W118: 0 | Y118: 0 | Z118: =Q118-(S118+T118+U118+W118+Y118) -> -8500000 | AA118: State Government funds
C119: 1.3.47 | D119: Annual School Grant (Monthly Disbursement to LGAs N500,000 per LGA for 23LGAs) | E119: To aid operational cost for effective service delivery in LGAs. | F119: 23 | G119: 23 LGAs will receive monthly grant | H119: NA | I119: Teachers | N119: 46142 | O119: 23 LGAs will receive monthly grant | Q119: =F119*P119 -> 0 | S119: 0 | T119: 0 | U119: 11500000 | W119: 0 | Y119: 0 | Z119: =Q119-(S119+T119+U119+W119+Y119) -> -11500000 | AA119: State Government funds
C120: 1.3.48 | D120: Annual School Grant (Monthly Disbursement to Schools N70,000 per school for 3,000 schools) | E120: To aid operational cost for effective service delivery in schools. | F120: 3000 | G120: 3,000No of schools funded | H120: NA | I120: All Learners and Teachers | N120: 46142 | O120: 3,000No of schools funded | Q120: =F120*P120 -> 0 | S120: 0 | T120: 0 | U120: 210000000 | W120: 0 | Y120: 0 | Z120: =Q120-(S120+T120+U120+W120+Y120) -> -210000000 | AA120: State Government funds
C121: 1.3.49 | D121: External works at UBEC Smart School Adaka, Makurdi | E121: To curb the effect of erosion and create conducive school environment | F121: 1 | G121: Improve external works at UBEC Smart School Adaka, Makurdi | H121: NA | I121: All Learners and Teachers | N121: 46142 | O121: External works and erosion control done at UBEC Smart School, Adaka | P121: 47140302 | Q121: =F121*P121 -> 47140302 | S121: 0 | T121: 47140302 | U121: 0 | W121: 0 | Y121: 0 | Z121: =Q121-(S121+T121+U121+W121+Y121) -> 0 | AA121: The renovation works will enable pupils and teachers to access the ECCDE section of the school that became unaccessable due poor maintenance
C122: 1.3.50 | D122: SBMC incentives for retained out of school children (OOSC) | E122: To encourage retention of OOSC | F122: 1200 | G122: 1200 OOSC will benefit from scholarship | H122: 1200 | I122: All Learners and Teachers | N122: 46142 | O122: Scholarship disbursement will be implemented | P122: 10946.466 | Q122: =F122*P122 -> 13135760 | S122: 0 | T122: 13135760 | U122: 0 | W122: 0 | Y122: 0 | Z122: =Q122-(S122+T122+U122+W122+Y122) -> -4.0046871e-07
C123: TOTAL | Q123: =SUM(Q73:Q122) -> 3.5546426e+08 | S123: =SUM(S73:S122) -> 0 | T123: =SUM(T73:T122) -> 3.5546426e+08 | U123: =SUM(U73:U122) -> 230000000 | V123: =SUM(W73:W122,Y73:Y122) -> 0 | Z123: =SUM(Z73:Z122) -> -2.3e+08
C125: S/N | D125: Activity | E125: Rationale/Reason for choice of activity | F125: Quantity | G125: Expected output | H125: Number of expected beneficiaries (OOSC) | I125: Target group (Select from the drop-down) | J125: Timeline (Shade as applicable) | N125: Expected due date MM-DD-YYYY | O125: Achievement indicator (% of project completed) | P125: Unit cost | Q125: Total cost (No input required) | R125: Implementation strategy (Select from the drop-down list) | S125: Resource mapping | Z125: Funding gap | AA125: Remarks
S126: Government fund | V126: Development partner 1 | X126: Development partner 2
J127: Q1 | K127: Q2 | L127: Q3 | M127: Q4 | S127: State Government education budget | T127: UBEC matching grant | U127: Unconditional grants/Emergency funds | V127: Name | W127: Amount | X127: Name | Y127: Amount | Z127: (No input required)
C128: Enabler (Matching grant): Supervision and Project monitoring of ongoing infrastructure activities
C129: 1 | D129: Project Supervision and Monitoring, Maintenance of supervision and monitoring vehicles, Monitoring and evaluation reports (UBEC/SUBEB joint monitoring inclusive | E129: To ensure quality and maintenance of standard. To ensure maximum value for money | F129: 16 | G129: 3,352No of projects supervised and monitored | H129: NA | I129: All Learners and Teachers | N129: 31/04/2026 | O129: 100% COMPLETED | P129: 3125000 | Q129: =F129*P129 -> 50000000 | R129: NCB | S129: 0 | T129: 50000000 | U129: 0 | W129: 0 | Y129: 0 | Z129: =Q129-(S129+T129+U129+W129+Y129) -> 0
C130: 2 | D130: HP Color laser jet M5225N Printer | E130: To facilitate Office Work | F130: 1 | G130: Production of Contract Documents | H130: NA | I130: All Learners and Teachers | N130: 31/04/2026 | O130: 100% Completed | P130: 8400000 | Q130: =F130*P130 -> 8400000 | R130: Request for quotation | S130: 0 | T130: 8400000 | U130: 0 | W130: 0 | Y130: 0 | Z130: =Q130-(S130+T130+U130+W130+Y130) -> 0 | AA130: The price covers taxes, delivery services and installation
C131: 3 | D131: Allowance/Acommadation/Feeding for Project Monitoring Team 5-Persons @125,000.00= N625,000.00/days | E131: To Ensure Proper Monitoring/Supervision of Contracts | F131: 16 | G131: Effective Physical Facility delivery | H131: NA | I131: All Learners and Teachers | N131: 31/04/2026 | O131: 100% COMPLETED | P131: 625000 | Q131: =F131*P131 -> 10000000 | R131: E-payment/Cash transfer | S131: 0 | T131: 10000000 | U131: 0 | W131: 0 | Y131: 0 | Z131: =Q131-(S131+T131+U131+W131+Y131) -> 0
C132: 4 | D132: Consultancy for Quantity Surveying | E132: To ensure construction costs and contracts valuation | F132: 1 | G132: Effective Physical Facility delivery | H132: NA | I132: All Learners and Teachers | N132: 31/04/2026 | O132: 100% COMPLETED | P132: 42655711 | Q132: =F132*P132 -> 42655711 | R132: E-payment/Cash transfer | S132: 0 | T132: 42655711 | U132: 0 | W132: 0 | Y132: 0 | Z132: =Q132-(S132+T132+U132+W132+Y132) -> 0.0040000007
C133: 5 | D133: HP Pavilion Core i7 1TB SSD, 16GB Ram Laptop Computer | E133: To ensure construction costs and contracts valuation audit | F133: 2 | G133: Effective Physical Facility delivery | H133: NA | I133: All Learners and Teachers | N133: 31/04/2026 | O133: 2 Laptops will be acquired | P133: 3564996.2 | Q133: =F133*P133 -> 7129992.4 | R133: E-payment/Cash transfer | S133: 0 | T133: 7129992.4 | U133: 0 | W133: 0 | Y133: 0 | Z133: =Q133-(S133+T133+U133+W133+Y133) -> -0.0030460004 | AA133: The price covers taxes, delivery services and installation
C134: 6 | P134: 0 | Q134: =F134*P134 -> 0 | S134: 0 | T134: 0 | U134: 0 | W134: 0 | Y134: 0 | Z134: =Q134-(S134+T134+U134+W134+Y134) -> 0
C135: 7 | P135: 0 | Q135: =F135*P135 -> 0 | S135: 0 | T135: 0 | U135: 0 | W135: 0 | Y135: 0 | Z135: =Q135-(S135+T135+U135+W135+Y135) -> 0
C136: 8 | P136: 0 | Q136: =F136*P136 -> 0 | S136: 0 | T136: 0 | U136: 0 | W136: 0 | Y136: 0 | Z136: =Q136-(S136+T136+U136+W136+Y136) -> 0
C137: 9 | P137: 0 | Q137: =F137*P137 -> 0 | S137: 0 | T137: 0 | U137: 0 | W137: 0 | Y137: 0 | Z137: =Q137-(S137+T137+U137+W137+Y137) -> 0
C138: 10 | P138: 0 | Q138: =F138*P138 -> 0 | S138: 0 | T138: 0 | U138: 0 | W138: 0 | Y138: 0 | Z138: =Q138-(S138+T138+U138+W138+Y138) -> 0
C139: 11 | P139: 0 | Q139: =F139*P139 -> 0 | S139: 0 | T139: 0 | U139: 0 | W139: 0 | Y139: 0 | Z139: =Q139-(S139+T139+U139+W139+Y139) -> 0
C140: 12 | P140: 0 | Q140: =F140*P140 -> 0 | S140: 0 | T140: 0 | U140: 0 | W140: 0 | Y140: 0 | Z140: =Q140-(S140+T140+U140+W140+Y140) -> 0
C141: 13 | P141: 0 | Q141: =F141*P141 -> 0 | S141: 0 | T141: 0 | U141: 0 | W141: 0 | Y141: 0 | Z141: =Q141-(S141+T141+U141+W141+Y141) -> 0
C142: 14 | P142: 0 | Q142: =F142*P142 -> 0 | S142: 0 | T142: 0 | U142: 0 | W142: 0 | Y142: 0 | Z142: =Q142-(S142+T142+U142+W142+Y142) -> 0
C143: 15 | P143: 0 | Q143: =F143*P143 -> 0 | S143: 0 | T143: 0 | U143: 0 | W143: 0 | Y143: 0 | Z143: =Q143-(S143+T143+U143+W143+Y143) -> 0
C144: 16 | P144: 0 | Q144: =F144*P144 -> 0 | S144: 0 | T144: 0 | U144: 0 | W144: 0 | Y144: 0 | Z144: =Q144-(S144+T144+U144+W144+Y144) -> 0
C145: 17 | P145: 0 | Q145: =F145*P145 -> 0 | S145: 0 | T145: 0 | U145: 0 | W145: 0 | Y145: 0 | Z145: =Q145-(S145+T145+U145+W145+Y145) -> 0
... C157: 29 | P157: 0 | Q157: =F157*P157 -> 0 | S157: 0 | T157: 0 | U157: 0 | W157: 0 | Y157: 0 | Z157: =Q157-(S157+T157+U157+W157+Y157) -> 0
C158: 6 | D158: Fueling of monitoring vehicles | F158: 16 | H158: NA | I158: All Learners and Teachers | P158: 1500000 | Q158: =F158*P158 -> 24000000 | R158: E-payment/Cash transfer | S158: 0 | T158: 24000000 | U158: 0 | W158: 0 | Y158: 0 | Z158: =Q158-(S158+T158+U158+W158+Y158) -> 0
C159: TOTAL | Q159: =SUM(Q129:Q158) -> 1.421857e+08 | S159: =SUM(S129:S158) -> 0 | T159: =SUM(T129:T158) -> 1.421857e+08 | U159: =SUM(U129:U158) -> 0 | V159: =SUM(W129:W158,Y129:Y158) -> 0 | Z159: =SUM(Z129:Z158) -> 0.00095400028
C163: S/N | D163: Activity | E163: Rationale/Reason for choice of activity | F163: Quantity | G163: Expected output | H163: Number of expected beneficiaries (OOSC) | I163: Target group (Select from the drop-down) | J163: Timeline (Shade as applicable) | N163: Expected due date MM-DD-YYYY | O163: Achievement indicator (% of project completed) | P163: Unit cost | Q163: Total cost | R163: Implementation strategy (Select from the drop-down list) | S163: Resource mapping | Z163: Funding gap | AA163: Remarks
S164: Government fund | V164: Development partner 1 | X164: Development partner 2
J165: Q1 | K165: Q2 | L165: Q3 | M165: Q4 | S165: State Government education budget | T165: UBEC matching grant | U165: Unconditional grants/Emergency funds | V165: Name | W165: Amount | X165: Name | Y165: Amount | Z165: (No input required)
C166: Enabler: Partnerships and cross-sector collaboration to expand access to basic education
...

Sheet Sports Development
A2: S/N | B2: Click the rows below to go the sports pillars type you would like to enter
A3: 1 | B3: Procurement of sports equipments
A4: 2 | B4: Sports Competitions
A5: 3 | B5: Publicity and Administrations
A6: 4 | B6: Supervision, Assessment and Verification
A7: 5 | B7: Annexus: List of beneficiary schools for sports equipment
G9: Total Procurement cost
B10: 1 | C10: Procurement of sport equipments | H10: =SUM(H11+H36+H61+H86+H111) -> 86644756
B11: 1.A.Type of Sport/Game: FOOTBAL | H11: =SUM(G14:G34) -> 46015762
B12: S/N | C12: Code | D12: Item description | E12: Qty | F12: Unit cost | G12: Total cost (No input required)
B14: 1 | C14: UBEC/SUBEB/SP/001-023/2025 | D14: Construction of mini-football fields (grass) with Installation of galvanize iron pipe goal post with improved 400m running tracks in selected schools | E14: 23 | F14: 2000685.3 | G14: =E14*F14 -> 46015762
G15: =E15*F15 -> 0
B16: 3 | F16: 0 | G16: =E16*F16 -> 0
B17: 4 | F17: 0 | G17: =E17*F17 -> 0
B18: 5 | F18: 0 | G18: =E18*F18 -> 0
B19: 6 | F19: 0 | G19: =E19*F19 -> 0
B20: 7 | F20: 0 | G20: =E20*F20 -> 0
B21: 8 | F21: 0 | G21: =E21*F21 -> 0
B22: 9 | F22: 0 | G22: =E22*F22 -> 0
B23: 10 | F23: 0 | G23: =E23*F23 -> 0
B24: 11 | F24: 0 | G24: =E24*F24 -> 0
B25: 12 | F25: 0 | G25: =E25*F25 -> 0
B26: 13 | F26: 0 | G26: =E26*F26 -> 0
B27: 14 | F27: 0 | G27: =E27*F27 -> 0
... B33: 20 | F33: 0 | G33: =E33*F33 -> 0
D34: Insert new row as necessary above this line | F34: 0 | G34: =E34*F34 -> 0
B36: 1.B. Type of Sport/Game: CHESS | H36: =SUM(G39:G59) -> 2300000
B37: S/N | C37: Code | D37: Item description | E37: Qty | F37: Unit cost | G37: Total cost (No input required)
B39: 1 | C39: UBEC/SUBEB/SP/024-115/2025 | D39: Chess game (4 per school) | E39: 92 | F39: 25000 | G39: =E39*F39 -> 2300000
B40: 2 | F40: 0 | G40: =E40*F40 -> 0
B41: 3 | F41: 0 | G41: =E41*F41 -> 0
B42: 4 | F42: 0 | G42: =E42*F42 -> 0
B43: 5 | F43: 0 | G43: =E43*F43 -> 0
B44: 6 | F44: 0 | G44: =E44*F44 -> 0
B45: 7 | F45: 0 | G45: =E45*F45 -> 0
B46: 8 | F46: 0 | G46: =E46*F46 -> 0
B47: 9 | F47: 0 | G47: =E47*F47 -> 0
B48: 10 | F48: 0 | G48: =E48*F48 -> 0
B49: 11 | F49: 0 | G49: =E49*F49 -> 0
B50: 12 | F50: 0 | G50: =E50*F50 -> 0
B51: 13 | F51: 0 | G51: =E51*F51 -> 0
... B58: 20 | F58: 0 | G58: =E58*F58 -> 0
D59: Insert new row as necessary above this line | F59: 0 | G59: =E59*F59 -> 0
B61: 1.C. Type of Sport/Game: Procurement of Football equipment | H61: =SUM(G64:G84) -> 38328994
B62: S/N | C62: Code | D62: Item description | E62: Qty | F62: Unit cost | G62: Total cost (No input required)
B64: 1 | C64: NA | D64: Football (6-balls per school) | E64: 138 | F64: 50000 | G64: =E64*F64 -> 6900000
B65: 2 | C65: NA | D65: Football Jerseys (Set of 15 pairs) | E65: 23 | F65: 162500 | G65: =E65*F65 -> 3737500
B66: 3 | C66: NA | D66: Football Boot | E66: 253 | F66: 50000 | G66: =E66*F66 -> 12650000
B67: 4 | C67: NA | D67: Football Net | E67: 46 | F67: 87500 | G67: =E67*F67 -> 4025000
B68: 5 | C68: NA | D68: Football Hose) | E68: 253 | F68: 9998 | G68: =E68*F68 -> 2529494
B69: 6 | C69: NA | D69: Goalkeeper Handglove (Set of 2) | E69: 46 | F69: 62500 | G69: =E69*F69 -> 2875000
B70: 7 | C70: NA | D70: Corner Flags (set of 4 flexible flags) | E70: 92 | F70: 37500 | G70: =E70*F70 -> 3450000
B71: 8 | C71: NA | D71: Shin-guard | E71: 253 | F71: 5000 | G71: =E71*F71 -> 1265000
B72: 9 | C72: NA | D72: Athletic relay baton (set of 6) | E72: 23 | F72: 25000 | G72: =E72*F72 -> 575000
B73: 10 | C73: NA | D73: Stopwatch | E73: 23 | F73: 14000 | G73: =E73*F73 -> 322000
B74: 11 | F74: 0 | G74: =E74*F74 -> 0
B75: 12 | F75: 0 | G75: =E75*F75 -> 0
B76: 13 | F76: 0 | G76: =E76*F76 -> 0
B77: 14 | F77: 0 | G77: =E77*F77 -> 0
B78: 15 | F78: 0 | G78: =E78*F78 -> 0
B79: 16 | F79: 0 | G79: =E79*F79 -> 0
B80: 17 | F80: 0 | G80: =E80*F80 -> 0
B81: 18 | F81: 0 | G81: =E81*F81 -> 0
B82: 19 | F82: 0 | G82: =E82*F82 -> 0
B83: 20 | F83: 0 | G83: =E83*F83 -> 0
D84: Insert new row as necessary above this line | F84: 0 | G84: =E84*F84 -> 0
B86: 1.D. Type of Sport/Game: | H86: =SUM(G89:G109) -> 0
B87: S/N | C87: Code | D87: Item description | E87: Qty | F87: Unit cost | G87: Total cost (No input required)
B89: 1 | F89: 0 | G89: =E89*F89 -> 0
B90: 2 | F90: 0 | G90: =E90*F90 -> 0
B91: 3 | F91: 0 | G91: =E91*F91 -> 0
B92: 4 | F92: 0 | G92: =E92*F92 -> 0
B93: 5 | F93: 0 | G93: =E93*F93 -> 0
B94: 6 | F94: 0 | G94: =E94*F94 -> 0
B95: 7 | F95: 0 | G95: =E95*F95 -> 0
B96: 8 | F96: 0 | G96: =E96*F96 -> 0
B97: 9 | F97: 0 | G97: =E97*F97 -> 0
B98: 10 | F98: 0 | G98: =E98*F98 -> 0
B99: 11 | F99: 0 | G99: =E99*F99 -> 0
B100: 12 | F100: 0 | G100: =E100*F100 -> 0
... B108: 20 | F108: 0 | G108: =E108*F108 -> 0
D109: Insert new row as necessary above this line | F109: 0 | G109: =E109*F109 -> 0
B111: 1.E. Type of Sport/Game: | H111: =SUM(G114:G134) -> 0
B112: S/N | C112: Code | D112: Item description | E112: Qty | F112: Unit cost | G112: Total cost (No input required)
B114: 1 | F114: 0 | G114: =E114*F114 -> 0
B115: 2 | F115: 0 | G115: =E115*F115 -> 0
B116: 3 | F116: 0 | G116: =E116*F116 -> 0
B117: 4 | F117: 0 | G117: =E117*F117 -> 0
B118: 5 | F118: 0 | G118: =E118*F118 -> 0
B119: 6 | F119: 0 | G119: =E119*F119 -> 0
B120: 7 | F120: 0 | G120: =E120*F120 -> 0
B121: 8 | F121: 0 | G121: =E121*F121 -> 0
B122: 9 | F122: 0 | G122: =E122*F122 -> 0
B123: 10 | F123: 0 | G123: =E123*F123 -> 0
B124: 11 | F124: 0 | G124: =E124*F124 -> 0
B125: 12 | F125: 0 | G125: =E125*F125 -> 0
... B133: 20 | F133: 0 | G133: =E133*F133 -> 0
D134: Insert new row as necessary above this line | F134: 0 | G134: =E134*F134 -> 0
G136: Total cost of sports competitions
B137: 2 | C137: Sports competitions | H137: =SUM(H138,H163,H188,H213) -> 28287141
...

Sheet GSCCS
B3: Click the rows below to go the Green School and Climate Change and Safeguards (GSCCS) pillar type you would like to enter
B4: GSCCI Pillar 1: Greening schools/planting of trees
B5: GSCCI Pillar 2: Promoting entrepreneurial Greening curricula
B6: GSCCI Pillar 3: Teacher training and education system capacity
B7: GSCCI Pillar 4: Greening communities
B8: GSCCI Pillar 5: National Greening competitions
B9: GSCCI Pillar 6: Establishment of Green Clubs (Climate change clubs)
B10: Rearing of Small Animals/Aquatic Farming
B11: Safeguards and Waste Management Initiatives
B12: Supervision and monitoring of GSCCS initiatives | P12: GSCCS GRAND TOTAL | Q12: =SUM(P14,P62,P110,P158,P206,P254,P302,P373,P443) -> 1.421857e+08
P13: Total Cost: GSCCI Pillar 1 (No input required)
B14: GSCCI Pillar 1: Greening schools/planting of trees | P14: =SUM(P18:P58) -> 29999296
B15: Objective:
B16: S/N | C16: Activity/item description | D16: Quantity (Insert only numeric values) | E16: Name of School | F16: LGA | G16: Location (Rural/Urban) | H16: GPS coordinates | J16: Enterprise Code | K16: Target Group (Select from the drop-down) | L16: Implementation strategy (Select from the drop-down) | M16: Duration | N16: Expected outcome | O16: Unit cost | P16: Total cost (No input required) | Q16: Remark
H17: Longitude | I17: Latitude
B18: 1 | C18: Planting of Palm Trees | D18: 20 | E18: LGEA Primary School Igirgi | F18: VANDEIKYA | G18: Rural | H18: 6.813737 | I18: 9.043157 | J18: UBEC/SUBEB/GSCCI/2025/001 | K18: All Learners and Teachers | L18: Credit School account | M18: 4 Weeks | N18: 20 palm trees planted | O18: 37499.12 | P18: =D18*O18 -> 749982.4
B19: 2 | C19: Planting of Palm Trees | D19: 20 | E19: RCM Primary School Poor | F19: MAKURDI | G19: Urban | H19: 7.707576 | I19: 8.532451 | J19: UBEC/SUBEB/GSCCI/2025/002 | K19: All Learners and Teachers | L19: Credit School account | M19: 4 Weeks | N19: 20 palm trees planted | O19: 37499.12 | P19: =D19*O19 -> 749982.4
B20: 3 | C20: Planting of Palm Trees | D20: 20 | E20: RCM Primary School Ugye | F20: VANDEIKYA | G20: Rural | H20: 6.75072 | I20: 9.26667 | J20: UBEC/SUBEB/GSCCI/2025/003 | K20: All Learners and Teachers | L20: Credit School account | M20: 4 Weeks | N20: 20 palm trees planted | O20: 37499.12 | P20: =D20*O20 -> 749982.4
B21: 4 | C21: Planting of Palm Trees | D21: 20 | E21: LGEA PRIMARY SCHOOL ORNGUDUEM-MBATIAV | F21: GBOKO | G21: Rural | H21: 7.324427 | I21: 8.745795 | J21: UBEC/SUBEB/GSCCI/2025/004 | K21: All Learners and Teachers | L21: Credit School account | M21: 4 Weeks | N21: 20 palm trees planted | O21: 37499.12 | P21: =D21*O21 -> 749982.4
B22: 5 | C22: Planting of Palm Trees | D22: 20 | E22: LGEA Primary School, Mbakunde | F22: VANDEIKYA | G22: Rural | H22: 6.80222 | I22: 9.030277 | J22: UBEC/SUBEB/GSCCI/2025/005 | K22: All Learners and Teachers | L22: Credit School account | M22: 4 Weeks | N22: 20 palm trees planted | O22: 37499.12 | P22: =D22*O22 -> 749982.4
B23: 6 | C23: Planting of Palm Trees | D23: 20 | E23: LGEA Primary School Effiom Edumoga | F23: OKPOKWU | G23: Rural | H23: 6.972923 | I23: 7.923681 | J23: UBEC/SUBEB/GSCCI/2025/006 | K23: All Learners and Teachers | L23: Credit School account | M23: 4 Weeks | N23: 20 palm trees planted | O23: 37499.12 | P23: =D23*O23 -> 749982.4
B24: 7 | C24: Planting of Palm Trees | D24: 20 | E24: LGEA PRIMARY SCHOOL AYAR-MBALOM | F24: GWER | G24: Rural | H24: 7.501173 | I24: 8.442443 | J24: UBEC/SUBEB/GSCCI/2025/007 | K24: All Learners and Teachers | L24: Credit School account | M24: 4 Weeks | N24: 20 palm trees planted | O24: 37499.12 | P24: =D24*O24 -> 749982.4
B25: 8 | C25: Planting of Palm Trees | D25: 20 | E25: NKST PRIMARY SCHOOL ATUKPU | F25: GWER WEST | G25: Rural | H25: 7.551713 | I25: 8.1949462 | J25: UBEC/SUBEB/GSCCI/2025/008 | K25: All Learners and Teachers | L25: Credit School account | M25: 4 Weeks | N25: 20 palm trees planted | O25: 37499.12 | P25: =D25*O25 -> 749982.4
B26: 9 | C26: Planting of Palm Trees | D26: 20 | E26: LGEA SCIENCE PRIMARY SCHOOL TORDONGA | F26: KATSIN ALA | G26: Rural | H26: 7.23451 | I26: 9.64793 | J26: UBEC/SUBEB/GSCCI/2025/009 | K26: All Learners and Teachers | L26: Credit School account | M26: 4 Weeks | N26: 20 palm trees planted | O26: 37499.12 | P26: =D26*O26 -> 749982.4
B27: 10 | C27: Planting of Palm Trees | D27: 20 | E27: RCM PRIMARY SCHOOL ACHU | F27: GWER WEST | G27: Rural | H27: 7.43088 | I27: 8.15606 | J27: UBEC/SUBEB/GSCCI/2025/010 | K27: All Learners and Teachers | L27: Credit School account | M27: 4 Weeks | N27: 20 palm trees planted | O27: 37499.12 | P27: =D27*O27 -> 749982.4
B28: 11 | C28: Planting of Palm Trees | D28: 20 | E28: RCM PRIMARY SCHOOL TSE-TWAR | F28: KATSIN ALA | G28: Rural | H28: 7.459672 | I28: 9.447688 | J28: UBEC/SUBEB/GSCCI/2025/011 | K28: All Learners and Teachers | L28: Credit School account | M28: 4 Weeks | N28: 20 palm trees planted | O28: 37499.12 | P28: =D28*O28 -> 749982.4
B29: 12 | C29: Planting of Palm Trees | D29: 20 | E29: NKST UBE JSS TONGO | F29: KONSHISHA | G29: Rural | H29: 6.57288 | I29: 8.46406 | J29: UBEC/SUBEB/GSCCI/2025/012 | K29: All Learners and Teachers | L29: Credit School account | M29: 4 Weeks | N29: 20 palm trees planted | O29: 37499.12 | P29: =D29*O29 -> 749982.4
... B57: 40 | C57: Planting of Palm Trees | D57: 20 | E57: LGEA PRIMARY SCHOOL EFFE UGBOKOLO | F57: OKPOKWU | G57: Urban | H57: 7.191622 | I57: 7.7464893 | J57: UBEC/SUBEB/GSCCI/2025/040 | K57: All Learners and Teachers | L57: Credit School account | M57: 4 Weeks | N57: 20 palm trees planted | O57: 37499.12 | P57: =D57*O57 -> 749982.4
C58: Insert new row as necessary above this line | O58: 0 | P58: =D58*O58 -> 0
P61: Total Cost: GSCCI Pillar 2 (No input required)
B62: GSCCI Pillar 2: Promoting entrepreneurial Greening curricula | P62: =SUM(P66:P106) -> 1501856.8
B63: Objective:
B64: S/N | C64: Activity/item description | D64: Quantity (Insert only numeric values) | E64: Name of School | F64: LGA | G64: Location (Rural/Urban) | H64: GPS coordinates | J64: Enterprise Code | K64: Target Group (Select from the drop-down) | L64: Implementation strategy (Select from the drop-down) | M64: Duration | N64: Expected outcome | O64: Unit cost | P64: Total cost (No input required) | Q64: Remark
H65: Longitude | I65: Latitude
B66: 1 | C66: Procurement of greening curriculum guide | D66: 1 | E66: LGEA Primary School Igirgi | F66: VANDEIKYA | G66: Rural | H66: 6.813737 | I66: 9.043157 | J66: UBEC/SUBEB/GSCCI/2025/041 | K66: All Learners and Teachers | L66: Request for quotation | M66: 12 Weeks | N66: 1 Greening curriculum guide will be delivered | O66: 37546.42 | P66: =D66*O66 -> 37546.42
B67: 2 | C67: Procurement of greening curriculum guide | D67: 1 | E67: RCM Primary School Poor | F67: MAKURDI | G67: Urban | H67: 7.707576 | I67: 8.532451 | J67: UBEC/SUBEB/GSCCI/2025/042 | K67: All Learners and Teachers | L67: Request for quotation | M67: 12 Weeks | N67: 1 Greening curriculum guide will be delivered | O67: 37546.42 | P67: =D67*O67 -> 37546.42
B68: 3 | C68: Procurement of greening curriculum guide | D68: 1 | E68: RCM Primary School Ugye | F68: VANDEIKYA | G68: Rural | H68: 6.75072 | I68: 9.26667 | J68: UBEC/SUBEB/GSCCI/2025/043 | K68: All Learners and Teachers | L68: Request for quotation | M68: 12 Weeks | N68: 1 Greening curriculum guide will be delivered | O68: 37546.42 | P68: =D68*O68 -> 37546.42
B69: 4 | C69: Procurement of greening curriculum guide | D69: 1 | E69: LGEA PRIMARY SCHOOL ORNGUDUEM-MBATIAV | F69: GBOKO | G69: Rural | H69: 7.324427 | I69: 8.745795 | J69: UBEC/SUBEB/GSCCI/2025/044 | K69: All Learners and Teachers | L69: Request for quotation | M69: 12 Weeks | N69: 1 Greening curriculum guide will be delivered | O69: 37546.42 | P69: =D69*O69 -> 37546.42
B70: 5 | C70: Procurement of greening curriculum guide | D70: 1 | E70: LGEA Primary School, Mbakunde | F70: VANDEIKYA | G70: Rural | H70: 6.80222 | I70: 9.030277 | J70: UBEC/SUBEB/GSCCI/2025/045 | K70: All Learners and Teachers | L70: Request for quotation | M70: 12 Weeks | N70: 1 Greening curriculum guide will be delivered | O70: 37546.42 | P70: =D70*O70 -> 37546.42
B71: 6 | C71: Procurement of greening curriculum guide | D71: 1 | E71: LGEA Primary School Effiom Edumoga | F71: OKPOKWU | G71: Rural | H71: 6.972923 | I71: 7.923681 | J71: UBEC/SUBEB/GSCCI/2025/046 | K71: All Learners and Teachers | L71: Request for quotation | M71: 12 Weeks | N71: 1 Greening curriculum guide will be delivered | O71: 37546.42 | P71: =D71*O71 -> 37546.42
B72: 7 | C72: Procurement of greening curriculum guide | D72: 1 | E72: LGEA PRIMARY SCHOOL AYAR-MBALOM | F72: GWER | G72: Rural | H72: 7.501173 | I72: 8.442443 | J72: UBEC/SUBEB/GSCCI/2025/047 | K72: All Learners and Teachers | L72: Request for quotation | M72: 12 Weeks | N72: 1 Greening curriculum guide will be delivered | O72: 37546.42 | P72: =D72*O72 -> 37546.42
B73: 8 | C73: Procurement of greening curriculum guide | D73: 1 | E73: NKST PRIMARY SCHOOL ATUKPU | F73: GWER WEST | G73: Rural | H73: 7.551713 | I73: 8.1949462 | J73: UBEC/SUBEB/GSCCI/2025/048 | K73: All Learners and Teachers | L73: Request for quotation | M73: 12 Weeks | N73: 1 Greening curriculum guide will be delivered | O73: 37546.42 | P73: =D73*O73 -> 37546.42
B74: 9 | C74: Procurement of greening curriculum guide | D74: 1 | E74: LGEA SCIENCE PRIMARY SCHOOL TORDONGA | F74: KATSIN ALA | G74: Rural | H74: 7.23451 | I74: 9.64793 | J74: UBEC/SUBEB/GSCCI/2025/049 | K74: All Learners and Teachers | L74: Request for quotation | M74: 12 Weeks | N74: 1 Greening curriculum guide will be delivered | O74: 37546.42 | P74: =D74*O74 -> 37546.42
B75: 10 | C75: Procurement of greening curriculum guide | D75: 1 | E75: RCM PRIMARY SCHOOL ACHU | F75: GWER WEST | G75: Rural | H75: 7.43088 | I75: 8.15606 | J75: UBEC/SUBEB/GSCCI/2025/050 | K75: All Learners and Teachers | L75: Request for quotation | M75: 12 Weeks | N75: 1 Greening curriculum guide will be delivered | O75: 37546.42 | P75: =D75*O75 -> 37546.42
B76: 11 | C76: Procurement of greening curriculum guide | D76: 1 | E76: RCM PRIMARY SCHOOL TSE-TWAR | F76: KATSIN ALA | G76: Rural | H76: 7.459672 | I76: 9.447688 | J76: UBEC/SUBEB/GSCCI/2025/051 | K76: All Learners and Teachers | L76: Request for quotation | M76: 12 Weeks | N76: 1 Greening curriculum guide will be delivered | O76: 37546.42 | P76: =D76*O76 -> 37546.42
B77: 12 | C77: Procurement of greening curriculum guide | D77: 1 | E77: NKST UBE JSS TONGO | F77: KONSHISHA | G77: Rural | H77: 6.57288 | I77: 8.46406 | J77: UBEC/SUBEB/GSCCI/2025/052 | K77: All Learners and Teachers | L77: Request for quotation | M77: 12 Weeks | N77: 1 Greening curriculum guide will be delivered | O77: 37546.42 | P77: =D77*O77 -> 37546.42
... B105: 40 | C105: Procurement of greening curriculum guide | D105: 1 | E105: LGEA PRIMARY SCHOOL EFFE UGBOKOLO | F105: OKPOKWU | G105: Urban | H105: 7.191622 | I105: 7.7464893 | J105: UBEC/SUBEB/GSCCI/2025/080 | K105: All Learners and Teachers | L105: Request for quotation | M105: 12 Weeks | N105: 1 Greening curriculum guide will be delivered | O105: 37546.42 | P105: =D105*O105 -> 37546.42
C106: Insert new row as necessary above this line | O106: 0 | P106: =D106*O106 -> 0
P109: Total Cost: GSCCI Pillar 3 (No input required)
B110: GSCCI Pillar 3: Teacher training and education system capacity | P110: =SUM(P114:P154) -> 8160000
B111: Objective:
B112: S/N | C112: Activity/item description | D112: Quantity (Insert only numeric values) | E112: Name of School | F112: LGA | G112: Location (Rural/Urban) | H112: GPS coordinates | J112: Enterprise Code | K112: Target Group (Select from the drop-down) | L112: Implementation strategy (Select from the drop-down) | M112: Duration | N112: Expected outcome | O112: Unit cost | P112: Total cost (No input required) | Q112: Remark
H113: Longitude | I113: Latitude
B114: 1 | C114: Train teachers & school leaders on green teaching practices | D114: 2 | E114: LGEA Primary School Igirgi | F114: VANDEIKYA | G114: Rural | H114: 6.813737 | I114: 9.043157 | J114: UBEC/SUBEB/GSCCI/2025/081 | K114: Teachers | L114: Request for quotation | M114: 3 Days | N114: 2-Teachers trained in eco-education and Improved classroom climate content delivery | O114: 102000 | P114: =D114*O114 -> 204000
B115: 2 | C115: Train teachers & school leaders on green teaching practices | D115: 2 | E115: RCM Primary School Poor | F115: MAKURDI | G115: Urban | H115: 7.707576 | I115: 8.532451 | J115: UBEC/SUBEB/GSCCI/2025/082 | K115: Teachers | L115: Request for quotation | M115: 3 Days | N115: 2-Teachers trained in eco-education and Improved classroom climate content delivery | O115: 102000 | P115: =D115*O115 -> 204000
B116: 3 | C116: Train teachers & school leaders on green teaching practices | D116: 2 | E116: RCM Primary School Ugye | F116: VANDEIKYA | G116: Rural | H116: 6.75072 | I116: 9.26667 | J116: UBEC/SUBEB/GSCCI/2025/083 | K116: Teachers | L116: Request for quotation | M116: 3 Days | N116: 2-Teachers trained in eco-education and Improved classroom climate content delivery | O116: 102000 | P116: =D116*O116 -> 204000
B117: 4 | C117: Train teachers & school leaders on green teaching practices | D117: 2 | E117: LGEA PRIMARY SCHOOL ORNGUDUEM-MBATIAV | F117: GBOKO | G117: Rural | H117: 7.324427 | I117: 8.745795 | J117: UBEC/SUBEB/GSCCI/2025/084 | K117: Teachers | L117: Request for quotation | M117: 3 Days | N117: 2-Teachers trained in eco-education and Improved classroom climate content delivery | O117: 102000 | P117: =D117*O117 -> 204000
B118: 5 | C118: Train teachers & school leaders on green teaching practices | D118: 2 | E118: LGEA Primary School, Mbakunde | F118: VANDEIKYA | G118: Rural | H118: 6.80222 | I118: 9.030277 | J118: UBEC/SUBEB/GSCCI/2025/085 | K118: Teachers | L118: Request for quotation | M118: 3 Days | N118: 2-Teachers trained in eco-education and Improved classroom climate content delivery | O118: 102000 | P118: =D118*O118 -> 204000
B119: 6 | C119: Train teachers & school leaders on green teaching practices | D119: 2 | E119: LGEA Primary School Effiom Edumoga | F119: OKPOKWU | G119: Rural | H119: 6.972923 | I119: 7.923681 | J119: UBEC/SUBEB/GSCCI/2025/086 | K119: Teachers | L119: Request for quotation | M119: 3 Days | N119: 2-Teachers trained in eco-education and Improved classroom climate content delivery | O119: 102000 | P119: =D119*O119 -> 204000
B120: 7 | C120: Train teachers & school leaders on green teaching practices | D120: 2 | E120: LGEA PRIMARY SCHOOL AYAR-MBALOM | F120: GWER | G120: Rural | H120: 7.501173 | I120: 8.442443 | J120: UBEC/SUBEB/GSCCI/2025/087 | K120: Teachers | L120: Request for quotation | M120: 3 Days | N120: 2-Teachers trained in eco-education and Improved classroom climate content delivery | O120: 102000 | P120: =D120*O120 -> 204000
B121: 8 | C121: Train teachers & school leaders on green teaching practices | D121: 2 | E121: NKST PRIMARY SCHOOL ATUKPU | F121: GWER WEST | G121: Rural | H121: 7.551713 | I121: 8.1949462 | J121: UBEC/SUBEB/GSCCI/2025/088 | K121: Teachers | L121: Request for quotation | M121: 3 Days | N121: 2-Teachers trained in eco-education and Improved classroom climate content delivery | O121: 102000 | P121: =D121*O121 -> 204000
B122: 9 | C122: Train teachers & school leaders on green teaching practices | D122: 2 | E122: LGEA SCIENCE PRIMARY SCHOOL TORDONGA | F122: KATSIN ALA | G122: Rural | H122: 7.23451 | I122: 9.64793 | J122: UBEC/SUBEB/GSCCI/2025/089 | K122: Teachers | L122: Request for quotation | M122: 3 Days | N122: 2-Teachers trained in eco-education and Improved classroom climate content delivery | O122: 102000 | P122: =D122*O122 -> 204000
B123: 10 | C123: Train teachers & school leaders on green teaching practices | D123: 2 | E123: RCM PRIMARY SCHOOL ACHU | F123: GWER WEST | G123: Rural | H123: 7.43088 | I123: 8.15606 | J123: UBEC/SUBEB/GSCCI/2025/090 | K123: Teachers | L123: Request for quotation | M123: 3 Days | N123: 2-Teachers trained in eco-education and Improved classroom climate content delivery | O123: 102000 | P123: =D123*O123 -> 204000
B124: 11 | C124: Train teachers & school leaders on green teaching practices | D124: 2 | E124: RCM PRIMARY SCHOOL TSE-TWAR | F124: KATSIN ALA | G124: Rural | H124: 7.459672 | I124: 9.447688 | J124: UBEC/SUBEB/GSCCI/2025/091 | K124: Teachers | L124: Request for quotation | M124: 3 Days | N124: 2-Teachers trained in eco-education and Improved classroom climate content delivery | O124: 102000 | P124: =D124*O124 -> 204000
B125: 12 | C125: Train teachers & school leaders on green teaching practices | D125: 2 | E125: NKST UBE JSS TONGO | F125: KONSHISHA | G125: Rural | H125: 6.57288 | I125: 8.46406 | J125: UBEC/SUBEB/GSCCI/2025/092 | K125: Teachers | L125: Request for quotation | M125: 3 Days | N125: 2-Teachers trained in eco-education and Improved classroom climate content delivery | O125: 102000 | P125: =D125*O125 -> 204000
... B153: 40 | C153: Train teachers & school leaders on green teaching practices | D153: 2 | E153: LGEA PRIMARY SCHOOL EFFE UGBOKOLO | F153: OKPOKWU | G153: Urban | H153: 7.191622 | I153: 7.7464893 | J153: UBEC/SUBEB/GSCCI/2025/120 | K153: Teachers | L153: Request for quotation | M153: 3 Days | N153: 2-Teachers trained in eco-education and Improved classroom climate content delivery | O153: 102000 | P153: =D153*O153 -> 204000
C154: Insert new row as necessary above this line | O154: 0 | P154: =D154*O154 -> 0
P157: Total Cost: GSCCI Pillar 4 (No input required)
B158: GSCCI Pillar 4: Greening communities | P158: =SUM(P162:P202) -> 11748559
B159: Objective:
B160: S/N | C160: Activity/item description | D160: Quantity (Insert only numeric values) | E160: Name of School | F160: LGA | G160: Location (Rural/Urban) | H160: GPS coordinates | J160: Enterprise Code | K160: Target Group (Select from the drop-down) | L160: Implementation strategy (Select from the drop-down) | M160: Duration | N160: Expected outcome | O160: Unit cost | P160: Total cost (No input required) | Q160: Remark
H161: Longitude | I161: Latitude
B162: 1 | C162: Advocacy on Greening communities in the three senatorial zones of the State (Selected communities) | D162: 3 | E162: NA | F162: NA | G162: Rural | H162: NA | I162: NA | J162: NA | K162: All Learners and Teachers | L162: Credit staff concern account | M162: 6 Weeks | N162: Cleaner and greener school environments and Increased community participation in school projects | O162: 3916186.4 | P162: =D162*O162 -> 11748559
B163: 2 | O163: 0 | P163: =D163*O163 -> 0
B164: 3 | O164: 0 | P164: =D164*O164 -> 0
B165: 4 | O165: 0 | P165: =D165*O165 -> 0
B166: 5 | O166: 0 | P166: =D166*O166 -> 0
B167: 6 | O167: 0 | P167: =D167*O167 -> 0
B168: 7 | O168: 0 | P168: =D168*O168 -> 0
B169: 8 | O169: 0 | P169: =D169*O169 -> 0
B170: 9 | O170: 0 | P170: =D170*O170 -> 0
B171: 10 | O171: 0 | P171: =D171*O171 -> 0
B172: 11 | O172: 0 | P172: =D172*O172 -> 0
B173: 12 | O173: 0 | P173: =D173*O173 -> 0
B174: 13 | O174: 0 | P174: =D174*O174 -> 0
... B201: 40 | O201: 0 | P201: =D201*O201 -> 0
C202: Insert new row as necessary above this line | O202: 0 | P202: =D202*O202 -> 0
P205: Total Cost: GSCCI Pillar 5 (No input required)
B206: GSCCI Pillar 5: National Greening competitions | P206: =SUM(P210:P250) -> 8183139.7
B207: Objective:
B208: S/N | C208: Activity/item description | D208: Quantity (Insert only numeric values) | E208: Name of School | F208: LGA | G208: Location (Rural/Urban) | H208: GPS coordinates | J208: Enterprise Code | K208: Target Group (Select from the drop-down) | L208: Implementation strategy (Select from the drop-down) | M208: Duration | N208: Expected outcome | O208: Unit cost | P208: Total cost (No input required) | Q208: Remark
H209: Longitude | I209: Latitude
B210: 1 | C210: Organize inter-school debates, quizzes & exhibitions on greening issues and climate change | D210: 1 | E210: N/A | F210: N/A | G210: N/A | H210: N/A | I210: N/A | J210: N/A | L210: Quality and Cost Based | M210: 2 Weeks | N210: Raised awareness and healthy competition on green issues | O210: 3739523.4 | P210: =D210*O210 -> 3739523.4
B211: 2 | C211: Award top 3 LGAs and 9 schools that have achieved green school environment and effectively practicing climate change mitigation | D211: 1 | E211: N/A | F211: N/A | G211: N/A | H211: N/A | I211: N/A | J211: N/A | L211: Quality and Cost Based | M211: 2 Weeks | N211: Raised awareness and healthy competition on green issues | O211: 1443616.3 | P211: =D211*O211 -> 1443616.3
B212: 3 | C212: Publicize events statewide | D212: 1 | E212: N/A | F212: N/A | G212: N/A | H212: N/A | I212: N/A | J212: N/A | L212: Quality and Cost Based | M212: 2 Weeks | N212: Visibility of GSCCI program | O212: 3000000 | P212: =D212*O212 -> 3000000
B213: 4 | O213: 0 | P213: =D213*O213 -> 0
B214: 5 | O214: 0 | P214: =D214*O214 -> 0
B215: 6 | O215: 0 | P215: =D215*O215 -> 0
B216: 7 | O216: 0 | P216: =D216*O216 -> 0
B217: 8 | O217: 0 | P217: =D217*O217 -> 0
...

Sheet Pillar 2 - Quality
B2: Click to return to welcome page
B4: Pillar 2: Enhance Quality of Teaching and Learning
G7: HOPE-DLI | H7: UBE Pillar
C8: Click to move to each sub-theme/section
C9: Priority initiative 2.1 (Matching grant): Ensure implementation of revised basic education curriculum across schools
C10: Priority initiative 2.2: Provision of adequate Teaching and Learning Materials (TLMs) for schools
C11: Priority initiative 2.3: Teacher/ education managers training and capacity building
C12: Enabler-matching grant Intervention: Quality Assurance monitoring (other)
C13: Enabler-matching grant: Levergaing digitalization to improve quality of basic education (ICT and Data Platform)
C14: Matching Grant Intervention: Sports Development
C15: Enabler-matching Grant Intervention: Green School and Climate Change and Safeguards (GSCCS)
C17: S/N | D17: Activity | E17: Objective | F17: Quantity | G17: Expected output | H17: Achievement indicator (% of activity completed) | I17: Target group (Select from the drop-down) | J17: Timeline (Shade as applicable) | N17: Expected start date MM-DD-YYYY | O17: Expected due date MM-DD-YYYY | P17: Unit cost | Q17: Total cost (No input required) | R17: Implementation strategy (Select from the drop-down list) | S17: Resource mapping | Z17: Funding gap (No input required) | AA17: Remarks
S18: Government fund | V18: Development partner 1 | X18: Development partner 2
J19: Q1 | K19: Q2 | L19: Q3 | M19: Q4 | S19: State education budget | T19: UBEC matching grant | U19: Unconditional grants/Emergency funds | V19: Name | W19: Amount | X19: Name | Y19: Amount
C20: Priority initiative 2.1 (Matching grant): Ensure implementation of revised basic education curriculum across schools
C21: 2.1.1 | D21: Purchase of 12000 copies of revised Basic education curriculum from NERDC: 50% public and 20% private schools respectively) | E21: In accordance with the Nigerian Educational Research and Development Council's (NERDC) standards, to guarantee that all public basic education schools in the state have access to the most up-to-date, nationally recognized curriculum materials in order to support consistent, pertinent, and competency-based teaching and learning. | F21: 12000 | G21: Widespread distribution and use of standardized, up-to-date curriculum materials across public basic education schools in the state, enabling consistent, competency-based teaching and improved instructional planning. | H21: 12000 curriculum purchased | I21: State level | N21: 45962 | O21: 45688 | P21: 8294.166 | Q21: =F21*P21 -> 99529992 | R21: Single source/Direct contracting | S21: 0 | T21: 99529992 | U21: 0 | W21: 0 | Y21: 0 | Z21: =Q21-SUM(S21:U21, W21,Y21) -> 0.00056791306
C22: 2.1.2 | D22: Distribution of 12000 copies of revised Basic education curriculum from NERDC to basic schools in 23 LGAs | E22: All public basic education schools in the 23 Local Government Areas (LGAs) of Benue State must have broad access to the nationally updated curriculum in order to standardize teaching materials, enhance instructional design, and improve learning outcomes in accordance with NERDC and UBEC guidelines. | F22: 23 | G22: All public basic education schools across the 23 LGAs are equipped with the updated NERDC curriculum, enabling standardized, quality-driven teaching and learning statewide | H22: 12000 Curriculum distributed | I22: State level | N22: 45962 | O22: 45688 | P22: 309099.36 | Q22: =F22*P22 -> 7109285.2 | R22: E-payment/Cash transfer | S22: 0 | T22: 7109285.2 | U22: 0 | W22: 0 | Y22: 0 | Z22: =Q22-SUM(S22:U22, W22,Y22) -> -0.00100007
C23: 2.1.3 | D23: Curriculum Orientation and sensitization campaigns at the three senatorial zones in the State | E23: To enhance effective implementation of the curriculum | F23: 3 | G23: Sensitize all Basic Education stakeholders in the state on the relevance of revised Basic education curriculum | H23: All the three senatorial zone in the state will receive the information | I23: State level | N23: 45962 | O23: 45688 | P23: 4739523.4 | Q23: =F23*P23 -> 14218570 | R23: Request for quotation | S23: 0 | T23: 14218570 | U23: 0 | W23: 0 | Y23: 0 | Z23: =Q23-SUM(S23:U23, W23,Y23) -> -0.0019999985
C24: 2.1.4 | D24: Teacher Training to improve curriculum implementation at the three senatorial zones in the State | E24: To prepare teachers for effective implementation of curriculum | F24: 3 | G24: train teachers on the implementation of the revised Basic education curriculum | H24: Selected Teachers will be trained | I24: State level | N24: 45962 | O24: 45688 | P24: 4739523.4 | Q24: =F24*P24 -> 14218570 | R24: Request for quotation | S24: 0 | T24: 14218570 | U24: 0 | W24: 0 | Y24: 0 | Z24: =Q24-SUM(S24:U24, W24,Y24) -> -0.0019999985
C25: 2.1.5 | D25: Monitoring and evaluation/ Tracking of curriculum implementation for the 23 LGAs | E25: To monitor the procure and distribution of revised Basic education curriculum | F25: 23 | G25: Track the implementation of the revised Basic education curriculum | H25: Effective implementation will be achieved | I25: State level | N25: 45962 | O25: 45688 | P25: 309099.36 | Q25: =F25*P25 -> 7109285.2 | R25: Request for quotation | S25: 0 | T25: 7109285.2 | U25: 0 | W25: 0 | Y25: 0 | Z25: =Q25-SUM(S25:U25, W25,Y25) -> 0.0039999299
C26: 2.1.6 | P26: 0 | Q26: =F26*P26 -> 0 | S26: 0 | T26: 0 | U26: 0 | W26: 0 | Y26: 0 | Z26: =Q26-SUM(S26:U26, W26,Y26) -> 0
C27: 2.1.7 | P27: 0 | Q27: =F27*P27 -> 0 | S27: 0 | T27: 0 | U27: 0 | W27: 0 | Y27: 0 | Z27: =Q27-SUM(S27:U27, W27,Y27) -> 0
C28: 2.1.8 | P28: 0 | Q28: =F28*P28 -> 0 | S28: 0 | T28: 0 | U28: 0 | W28: 0 | Y28: 0 | Z28: =Q28-SUM(S28:U28, W28,Y28) -> 0
C29: 2.1.9 | P29: 0 | Q29: =F29*P29 -> 0 | S29: 0 | T29: 0 | U29: 0 | W29: 0 | Y29: 0 | Z29: =Q29-SUM(S29:U29, W29,Y29) -> 0
C30: 2.1.10 | P30: 0 | Q30: =F30*P30 -> 0 | S30: 0 | T30: 0 | U30: 0 | W30: 0 | Y30: 0 | Z30: =Q30-SUM(S30:U30, W30,Y30) -> 0
C31: 2.1.11 | P31: 0 | Q31: =F31*P31 -> 0 | S31: 0 | T31: 0 | U31: 0 | W31: 0 | Y31: 0 | Z31: =Q31-SUM(S31:U31, W31,Y31) -> 0
C32: 2.1.12 | P32: 0 | Q32: =F32*P32 -> 0 | S32: 0 | T32: 0 | U32: 0 | W32: 0 | Y32: 0 | Z32: =Q32-SUM(S32:U32, W32,Y32) -> 0
C33: 2.1.13 | P33: 0 | Q33: =F33*P33 -> 0 | S33: 0 | T33: 0 | U33: 0 | W33: 0 | Y33: 0 | Z33: =Q33-SUM(S33:U33, W33,Y33) -> 0
C34: 2.1.14 | P34: 0 | Q34: =F34*P34 -> 0 | S34: 0 | T34: 0 | U34: 0 | W34: 0 | Y34: 0 | Z34: =Q34-SUM(S34:U34, W34,Y34) -> 0
C35: 2.1.15 | P35: 0 | Q35: =F35*P35 -> 0 | S35: 0 | T35: 0 | U35: 0 | W35: 0 | Y35: 0 | Z35: =Q35-SUM(S35:U35, W35,Y35) -> 0
C36: 2.1.16 | P36: 0 | Q36: =F36*P36 -> 0 | S36: 0 | T36: 0 | U36: 0 | W36: 0 | Y36: 0 | Z36: =Q36-SUM(S36:U36, W36,Y36) -> 0
C37: 2.1.17 | P37: 0 | Q37: =F37*P37 -> 0 | S37: 0 | T37: 0 | U37: 0 | W37: 0 | Y37: 0 | Z37: =Q37-SUM(S37:U37, W37,Y37) -> 0
... C50: 2.1.30 | P50: 0 | Q50: =F50*P50 -> 0 | S50: 0 | T50: 0 | U50: 0 | W50: 0 | Y50: 0 | Z50: =Q50-SUM(S50:U50, W50,Y50) -> 0
C51: TOTAL | Q51: =SUM(Q21:Q50) -> 1.421857e+08 | S51: =SUM(S21:S50) -> 0 | T51: =SUM(T21:T50) -> 1.421857e+08 | U51: =SUM(U21:U50) -> 0 | V51: =SUM(W21:W50,Y21:Y50) -> 0 | Z51: =SUM(Z21:Z50) -> -0.00043222401
C53: S/N | D53: Activity | E53: Objective | F53: Quantity | G53: Expected output | H53: Achievement indicator (% of activity completed) | I53: Target group (Select from the drop-down) | J53: Timeline | N53: Expected start date MM-DD-YYYY | O53: Expected due date MM-DD-YYYY | P53: Unit cost | Q53: Total cost (No input required) | R53: Implementation strategy (Select from the drop-down list) | S53: Resource mapping | Z53: Funding gap (No input required) | AA53: Remarks
S54: Government fund | V54: Development partner 1 | X54: Development partner 2
J55: Q1 | K55: Q2 | L55: Q3 | M55: Q4 | S55: State education budget | T55: UBEC matching grant | U55: Unconditional grants/Emergency funds | V55: Name | W55: Amount | X55: Name | Y55: Amount
C56: Priority initiative 2.2: Provision of adequate Teaching and Learning Materials (TLMs) for schools (Hope-EDU DLI)
C57: 2.2.1 | D57: ='Infrastructure Projects'!D1422 -> PROCUREMENT OF LITERACY AND NUMERACY TEXT/WORKBOOKS FOR PRIMARY SCHOOLS | E57: Providing sufficient TLMs to Basic Schools (Ratio 1:1 for the selected schools) | F57: 80000 | G57: 80,000No. TLMs will be delivered | H57: 100% Completion | I57: Schools | N57: 45962 | O57: 45688 | P57: ='Infrastructure Projects'!P1421 -> 721626000 | S57: 0 | T57: 722400000 | U57: 0 | W57: 0 | Y57: 0 | Z57: =Q57-SUM(S57:U57, W57,Y57) -> -722400000
C58: 2.2.2 | F58: 1 | P58: 722400000 | Q58: =F58*P58 -> 722400000 | S58: 0 | T58: 0 | U58: 0 | W58: 0 | Y58: 0 | Z58: =Q58-SUM(S58:U58, W58,Y58) -> 722400000
C59: 2.2.3 | P59: 0 | Q59: =F59*P59 -> 0 | S59: 0 | T59: 0 | U59: 0 | W59: 0 | Y59: 0 | Z59: =Q59-SUM(S59:U59, W59,Y59) -> 0
C60: 2.2.4 | P60: 0 | Q60: =F60*P60 -> 0 | S60: 0 | T60: 0 | U60: 0 | W60: 0 | Y60: 0 | Z60: =Q60-SUM(S60:U60, W60,Y60) -> 0
C61: 2.2.5 | P61: 0 | Q61: =F61*P61 -> 0 | S61: 0 | T61: 0 | U61: 0 | W61: 0 | Y61: 0 | Z61: =Q61-SUM(S61:U61, W61,Y61) -> 0
C62: 2.2.6 | P62: 0 | Q62: =F62*P62 -> 0 | S62: 0 | T62: 0 | U62: 0 | W62: 0 | Y62: 0 | Z62: =Q62-SUM(S62:U62, W62,Y62) -> 0
C63: 2.2.7 | P63: 0 | Q63: =F63*P63 -> 0 | S63: 0 | T63: 0 | U63: 0 | W63: 0 | Y63: 0 | Z63: =Q63-SUM(S63:U63, W63,Y63) -> 0
C64: 2.2.8 | P64: 0 | Q64: =F64*P64 -> 0 | S64: 0 | T64: 0 | U64: 0 | W64: 0 | Y64: 0 | Z64: =Q64-SUM(S64:U64, W64,Y64) -> 0
C65: 2.2.9 | P65: 0 | Q65: =F65*P65 -> 0 | S65: 0 | T65: 0 | U65: 0 | W65: 0 | Y65: 0 | Z65: =Q65-SUM(S65:U65, W65,Y65) -> 0
C66: 2.2.10 | P66: 0 | Q66: =F66*P66 -> 0 | S66: 0 | T66: 0 | U66: 0 | W66: 0 | Y66: 0 | Z66: =Q66-SUM(S66:U66, W66,Y66) -> 0
C67: 2.2.11 | P67: 0 | Q67: =F67*P67 -> 0 | S67: 0 | T67: 0 | U67: 0 | W67: 0 | Y67: 0 | Z67: =Q67-SUM(S67:U67, W67,Y67) -> 0
C68: 2.2.12 | P68: 0 | Q68: =F68*P68 -> 0 | S68: 0 | T68: 0 | U68: 0 | W68: 0 | Y68: 0 | Z68: =Q68-SUM(S68:U68, W68,Y68) -> 0
C69: 2.2.13 | P69: 0 | Q69: =F69*P69 -> 0 | S69: 0 | T69: 0 | U69: 0 | W69: 0 | Y69: 0 | Z69: =Q69-SUM(S69:U69, W69,Y69) -> 0
C70: 2.2.14 | P70: 0 | Q70: =F70*P70 -> 0 | S70: 0 | T70: 0 | U70: 0 | W70: 0 | Y70: 0 | Z70: =Q70-SUM(S70:U70, W70,Y70) -> 0
... C86: 2.2.30 | P86: 0 | Q86: =F86*P86 -> 0 | S86: 0 | T86: 0 | U86: 0 | W86: 0 | Y86: 0 | Z86: =Q86-SUM(S86:U86, W86,Y86) -> 0
C87: TOTAL | Q87: =SUM(Q57:Q86) -> 722400000 | S87: =SUM(S57:S86) -> 0 | T87: =SUM(T57:T86) -> 722400000 | U87: =SUM(U57:U86) -> 0 | V87: =SUM(W57:W86,Y57:Y86) -> 0 | Z87: =SUM(Z57:Z86) -> 0
C90: S/N | D90: Activity | E90: Objective | F90: Quantity | G90: Expected output | H90: Achievement indicator (% of activity completed) | I90: Target group (Select from the drop-down) | J90: Timeline | N90: Expected start date MM-DD-YYYY | O90: Expected due date MM-DD-YYYY | P90: Number of teachers/education managers required to be trained | Q90: Number of teachers/education managers planned to be trained | R90: Unit cost per teacher/education manager | S90: Total cost (No input required) | T90: Implementation strategy (Select from the drop-down list) | U90: Resource mapping | AB90: Funding gap (No input required) | AC90: Remarks
U91: Government fund | X91: Development partner 1 | Z91: Development partner 2
J92: Q1 | K92: Q2 | L92: Q3 | M92: Q4 | U92: State education budget | V92: UBEC matching grant | W92: Unconditional grants/Emergency funds | X92: Name | Y92: Amount | Z92: Name | AA92: Amount
C93: Priority initiative 2.3: Teacher/ education managers training and capacity building (Hope-EDU DLI)
C94: 2.3.1 | D94: Training for 9,700 teachers and mentors on structured pedagogy in 23 LGAs | E94: To equip teachers adequate pedagogical skills | F94: 9700 | G94: 9,700 teachers will be trained | H94: 9,700 received the teacher traing | I94: State level | N94: 45962 | O94: 45688 | R94: 102000 | S94: =F94*R94 -> 989400000 | T94: E-payment/Cash transfer | U94: 989400000 | V94: 0 | W94: 0 | Y94: 0 | AA94: 0 | AB94: =S94-SUM(U94:W94, Y94,AA94) -> 0
C95: 2.3.2 | R95: 0 | S95: =F95*R95 -> 0 | U95: 0 | V95: 0 | W95: 0 | Y95: 0 | AA95: 0 | AB95: =S95-SUM(U95:W95, Y95,AA95) -> 0
C96: 2.3.3 | R96: 0 | S96: =F96*R96 -> 0 | U96: 0 | V96: 0 | W96: 0 | Y96: 0 | AA96: 0 | AB96: =S96-SUM(U96:W96, Y96,AA96) -> 0
C97: 2.3.4 | R97: 0 | S97: =F97*R97 -> 0 | U97: 0 | V97: 0 | W97: 0 | Y97: 0 | AA97: 0 | AB97: =S97-SUM(U97:W97, Y97,AA97) -> 0
C98: 2.3.5 | R98: 0 | S98: =F98*R98 -> 0 | U98: 0 | V98: 0 | W98: 0 | Y98: 0 | AA98: 0 | AB98: =S98-SUM(U98:W98, Y98,AA98) -> 0
C99: 2.3.6 | R99: 0 | S99: =F99*R99 -> 0 | U99: 0 | V99: 0 | W99: 0 | Y99: 0 | AA99: 0 | AB99: =S99-SUM(U99:W99, Y99,AA99) -> 0
C100: 2.3.7 | R100: 0 | S100: =F100*R100 -> 0 | U100: 0 | V100: 0 | W100: 0 | Y100: 0 | AA100: 0 | AB100: =S100-SUM(U100:W100, Y100,AA100) -> 0
C101: 2.3.8 | R101: 0 | S101: =F101*R101 -> 0 | U101: 0 | V101: 0 | W101: 0 | Y101: 0 | AA101: 0 | AB101: =S101-SUM(U101:W101, Y101,AA101) -> 0
C102: 2.3.9 | R102: 0 | S102: =F102*R102 -> 0 | U102: 0 | V102: 0 | W102: 0 | Y102: 0 | AA102: 0 | AB102: =S102-SUM(U102:W102, Y102,AA102) -> 0
C103: 2.3.10 | R103: 0 | S103: =F103*R103 -> 0 | U103: 0 | V103: 0 | W103: 0 | Y103: 0 | AA103: 0 | AB103: =S103-SUM(U103:W103, Y103,AA103) -> 0
C104: 2.3.11 | R104: 0 | S104: =F104*R104 -> 0 | U104: 0 | V104: 0 | W104: 0 | Y104: 0 | AA104: 0 | AB104: =S104-SUM(U104:W104, Y104,AA104) -> 0
C105: 2.3.12 | R105: 0 | S105: =F105*R105 -> 0 | U105: 0 | V105: 0 | W105: 0 | Y105: 0 | AA105: 0 | AB105: =S105-SUM(U105:W105, Y105,AA105) -> 0
C106: 2.3.13 | R106: 0 | S106: =F106*R106 -> 0 | U106: 0 | V106: 0 | W106: 0 | Y106: 0 | AA106: 0 | AB106: =S106-SUM(U106:W106, Y106,AA106) -> 0
... C123: 2.3.30 | R123: 0 | S123: =F123*R123 -> 0 | U123: 0 | V123: 0 | W123: 0 | Y123: 0 | AA123: 0 | AB123: =S123-SUM(U123:W123, Y123,AA123) -> 0
C124: TOTAL | S124: =SUM(S94:S123) -> 989400000 | U124: =SUM(U94:U123) -> 989400000 | V124: =SUM(V94:V123) -> 0 | W124: =SUM(W94:W123) -> 0 | X124: =SUM(Y94:Y123,AA94:AA123) -> 0 | AB124: =SUM(AB94:AB123) -> 0
C129: S/N | D129: Activity | E129: Objective | F129: Quantity | G129: Location | H129: Achievement indicator (% of activity completed) | I129: Target group (Select from the drop-down) | J129: Timeline | N129: Expected outcome | O129: Unit cost | P129: Total cost (No input required) | Q129: Implementation strategy (Select from the drop-down list) | R129: Resource mapping | Y129: Funding gap (No input required) | Z129: Remarks
R130: Government fund | U130: Development partner 1 | W130: Development partner 2
J131: Q1 | K131: Q2 | L131: Q3 | M131: Q4 | R131: State education budget | S131: UBEC matching grant | T131: Unconditional grants/Emergency funds | U131: Name | V131: Amount | W131: Name | X131: Amount
C132: Enabler (Matching grant): Quality Assurance monitoring
C133: 1 | D133: Capacity building for QAOs and Headteachers/Principals on Quality Assurance Practices and Procedures for effective school monitoring | E133: To equip QAOs and school heads with adequate technical capacity to effecive carry out monitoring and evaluation | F133: 150 | G133: SUBEB Headquarter | H133: DQOs and school administrators will be trained on Quality Assurance Practices and Procedures | I133: State level | N133: 150 DQOs and Headteachers/Principals will be trained on Quality Assurance Practices and Procedures | O133: 102000 | P133: =F133*O133 -> 15300000 | R133: 0 | S133: 15300000 | T133: 0 | V133: 0 | X133: 0 | Y133: =P133-SUM(R133:T133, V133,X133) -> 0
C134: 2 | D134: Allowance for Management Supervision | E134: To enhance effective management monitoring | F134: 1 | G134: SUBEB Headquarter | H134: Effective Supervision by Management 100% acheived | I134: State level | N134: Effective Supervision by Management 100% acheived | O134: 2000000 | P134: =F134*O134 -> 2000000 | R134: 0 | S134: 2000000 | T134: 0 | V134: 0 | X134: 0 | Y134: =P134-SUM(R134:T134, V134,X134) -> 0
C135: 3 | P135: =F135*O135 -> 0 | R135: 0 | S135: 0 | T135: 0 | V135: 0 | X135: 0 | Y135: =P135-SUM(R135:T135, V135,X135) -> 0
C136: 4 | P136: =F136*O136 -> 0 | R136: 0 | S136: 0 | T136: 0 | V136: 0 | X136: 0 | Y136: =P136-SUM(R136:T136, V136,X136) -> 0
C137: 5 | P137: =F137*O137 -> 0 | R137: 0 | S137: 0 | T137: 0 | V137: 0 | X137: 0 | Y137: =P137-SUM(R137:T137, V137,X137) -> 0
C138: 2 | D138: Allowance for QA officers | E138: To ensure effective monitoring | F138: 30 | G138: SUBEB Headquarter | H138: Effective Supervision by QAOs 100% acheived | I138: State level | N138: 30 QAOs allowance will be acheived | O138: 192942.25 | P138: =F138*O138 -> 5788267.4 | R138: 0 | S138: 5788267.4 | T138: 0 | V138: 0 | X138: 0 | Y138: =P138-SUM(R138:T138, V138,X138) -> 0
C139: 7 | P139: =F139*O139 -> 0 | R139: 0 | S139: 0 | T139: 0 | V139: 0 | X139: 0 | Y139: =P139-SUM(R139:T139, V139,X139) -> 0
C140: 8 | P140: =F140*O140 -> 0 | R140: 0 | S140: 0 | T140: 0 | V140: 0 | X140: 0 | Y140: =P140-SUM(R140:T140, V140,X140) -> 0
C141: 3 | D141: Fieldwork; School Resumption, Exams, Follow-up, CQA 115 | E141: To caary out efficient quality assurance monitoring | F141: 361 | G141: Sample Schools | H141: 100% completion of monitoring visits | I141: State level | N141: 361 visits Completed | O141: 184279.78 | P141: =F141*O141 -> 66525000 | R141: 0 | S141: 66525000 | T141: 0 | V141: 0 | X141: 0 | Y141: =P141-SUM(R141:T141, V141,X141) -> -6.5565109e-07
C142: 4 | D142: Maintenance of all monitoring vehicles | E142: To facilitate easy mobility | F142: 1 | G142: Sample Schools | H142: To ensure the efficiency and effectiveness in the runing of schools programme and activities. | I142: State level | N142: 361 visits Completed | O142: 19344278 | P142: =F142*O142 -> 19344278 | R142: 0 | S142: 19344278 | T142: 0 | V142: 0 | X142: 0 | Y142: =P142-SUM(R142:T142, V142,X142) -> 0
C143: 5 | P143: =F143*O143 -> 0 | R143: 0 | S143: 0 | T143: 0 | V143: 0 | X143: 0 | Y143: =P143-SUM(R143:T143, V143,X143) -> 0
C144: 12 | O144: 0 | P144: =F144*O144 -> 0 | R144: 0 | S144: 0 | T144: 0 | V144: 0 | X144: 0 | Y144: =P144-SUM(R144:T144, V144,X144) -> 0
C145: 13 | O145: 0 | P145: =F145*O145 -> 0 | R145: 0 | S145: 0 | T145: 0 | V145: 0 | X145: 0 | Y145: =P145-SUM(R145:T145, V145,X145) -> 0
C146: 14 | O146: 0 | P146: =F146*O146 -> 0 | R146: 0 | S146: 0 | T146: 0 | V146: 0 | X146: 0 | Y146: =P146-SUM(R146:T146, V146,X146) -> 0
C147: 15 | O147: 0 | P147: =F147*O147 -> 0 | R147: 0 | S147: 0 | T147: 0 | V147: 0 | X147: 0 | Y147: =P147-SUM(R147:T147, V147,X147) -> 0
C148: 16 | O148: 0 | P148: =F148*O148 -> 0 | R148: 0 | S148: 0 | T148: 0 | V148: 0 | X148: 0 | Y148: =P148-SUM(R148:T148, V148,X148) -> 0
C149: 17 | O149: 0 | P149: =F149*O149 -> 0 | R149: 0 | S149: 0 | T149: 0 | V149: 0 | X149: 0 | Y149: =P149-SUM(R149:T149, V149,X149) -> 0
C150: 18 | O150: 0 | P150: =F150*O150 -> 0 | R150: 0 | S150: 0 | T150: 0 | V150: 0 | X150: 0 | Y150: =P150-SUM(R150:T150, V150,X150) -> 0
C151: 19 | O151: 0 | P151: =F151*O151 -> 0 | R151: 0 | S151: 0 | T151: 0 | V151: 0 | X151: 0 | Y151: =P151-SUM(R151:T151, V151,X151) -> 0
C152: 20 | O152: 0 | P152: =F152*O152 -> 0 | R152: 0 | S152: 0 | T152: 0 | V152: 0 | X152: 0 | Y152: =P152-SUM(R152:T152, V152,X152) -> 0
C153: 21 | O153: 0 | P153: =F153*O153 -> 0 | R153: 0 | S153: 0 | T153: 0 | V153: 0 | X153: 0 | Y153: =P153-SUM(R153:T153, V153,X153) -> 0
C154: 22 | O154: 0 | P154: =F154*O154 -> 0 | R154: 0 | S154: 0 | T154: 0 | V154: 0 | X154: 0 | Y154: =P154-SUM(R154:T154, V154,X154) -> 0
C155: 23 | P155: =F155*O155 -> 0 | R155: 0 | T155: 0 | V155: 0 | X155: 0 | Y155: =P155-SUM(R155:T155, V155,X155) -> 0
...

Sheet Pillar 3 - Systems Optimization
B2: Click to return to welcome page
B4: Pillar 3: Optimize institutional systems for quality service delivery
H6: HOPE-DLI | I6: UBE Pillar
C7: Click to move to each sub-theme
C8: Priority initiative 3.1: Optimize organizational structure, guidelines, and personnel capacity to effectively deliver on mandate and impact
C9: Priority initiative 3.2: Ensure transparent and effective financial management at state and LGA levels
C10: Priority initiative 3.3: Strengthen SUBEB’s brand reputation with stakeholders through strategic engagements, media, and other activities
C11: Priority initiative 3.4: Improve coordination and implementation of basic education programs with MoE, LGEAs, UBEC and other stakeholders
C12: Enabler: Strengthen performance management, and routine monitoring and evaluation of Basic Education Programs
C13: Enabler: Instituting a framework for quality assurance to improve access to basic education
C15: S/N | D15: Activity | E15: Quantity (Insert only numeric values) | F15: Objective | G15: Expected output | H15: Achievement indicator | I15: Target group (Select from the drop-down) | J15: Timeline (Shade as applicable) | N15: Expected start date MM-DD-YYYY | O15: Expected due date MM-DD-YYYY | P15: Unit Cost | Q15: Total cost (No input required) | R15: Implementation strategy (Select from the drop-down list) | S15: Resource mapping | Z15: Funding gap (No input required) | AA15: Remarks
S16: Government fund | V16: Development partner 1 | X16: Development partner 2
J17: Q1 | K17: Q2 | L17: Q3 | M17: Q4 | S17: State education budget | T17: UBEC matching grant | U17: Unconditional grants/Emergency funds | V17: Name | W17: Amount | X17: Name | Y17: Amount
C19: Priority initiative 3.1: Optimize organizational structure, guidelines, and personnel capacity to effectively deliver on mandate and impact
C20: 3.1.1 | D20: Conduct workshop to update organizational structure and operational guidelines | P20: 0 | Q20: =E20*P20 -> 0 | S20: 0 | T20: 0 | U20: 0 | W20: 0 | Y20: 0 | Z20: =Q20-SUM(S20:U20, W20,Y20) -> 0
C21: 3.1.2 | P21: 0 | Q21: =E21*P21 -> 0 | S21: 0 | T21: 0 | U21: 0 | W21: 0 | Y21: 0 | Z21: =Q21-SUM(S21:U21, W21,Y21) -> 0
C22: 3.1.3 | P22: 0 | Q22: =E22*P22 -> 0 | S22: 0 | T22: 0 | U22: 0 | W22: 0 | Y22: 0 | Z22: =Q22-SUM(S22:U22, W22,Y22) -> 0
C23: 3.1.4 | P23: 0 | Q23: =E23*P23 -> 0 | S23: 0 | T23: 0 | U23: 0 | W23: 0 | Y23: 0 | Z23: =Q23-SUM(S23:U23, W23,Y23) -> 0
C24: 3.1.5 | P24: 0 | Q24: =E24*P24 -> 0 | S24: 0 | T24: 0 | U24: 0 | W24: 0 | Y24: 0 | Z24: =Q24-SUM(S24:U24, W24,Y24) -> 0
C25: 3.1.6 | P25: 0 | Q25: =E25*P25 -> 0 | S25: 0 | T25: 0 | U25: 0 | W25: 0 | Y25: 0 | Z25: =Q25-SUM(S25:U25, W25,Y25) -> 0
C26: 3.1.7 | P26: 0 | Q26: =E26*P26 -> 0 | S26: 0 | T26: 0 | U26: 0 | W26: 0 | Y26: 0 | Z26: =Q26-SUM(S26:U26, W26,Y26) -> 0
C27: 3.1.8 | P27: 0 | Q27: =E27*P27 -> 0 | S27: 0 | T27: 0 | U27: 0 | W27: 0 | Y27: 0 | Z27: =Q27-SUM(S27:U27, W27,Y27) -> 0
C28: 3.1.9 | P28: 0 | Q28: =E28*P28 -> 0 | S28: 0 | T28: 0 | U28: 0 | W28: 0 | Y28: 0 | Z28: =Q28-SUM(S28:U28, W28,Y28) -> 0
C29: 3.1.10 | P29: 0 | Q29: =E29*P29 -> 0 | S29: 0 | T29: 0 | U29: 0 | W29: 0 | Y29: 0 | Z29: =Q29-SUM(S29:U29, W29,Y29) -> 0
C30: 3.1.11 | P30: 0 | Q30: =E30*P30 -> 0 | S30: 0 | T30: 0 | U30: 0 | W30: 0 | Y30: 0 | Z30: =Q30-SUM(S30:U30, W30,Y30) -> 0
C31: 3.1.12 | P31: 0 | Q31: =E31*P31 -> 0 | S31: 0 | T31: 0 | U31: 0 | W31: 0 | Y31: 0 | Z31: =Q31-SUM(S31:U31, W31,Y31) -> 0
C32: 3.1.13 | P32: 0 | Q32: =E32*P32 -> 0 | S32: 0 | T32: 0 | U32: 0 | W32: 0 | Y32: 0 | Z32: =Q32-SUM(S32:U32, W32,Y32) -> 0
... C49: 3.1.30 | P49: 0 | Q49: =E49*P49 -> 0 | S49: 0 | T49: 0 | U49: 0 | W49: 0 | Y49: 0 | Z49: =Q49-SUM(S49:U49, W49,Y49) -> 0
C50: TOTAL | Q50: =SUM(Q20:Q49) -> 0 | S50: =SUM(S20:S49) -> 0 | T50: =SUM(T20:T49) -> 0 | U50: =SUM(U20:U49) -> 0 | V50: =SUM(W20:W49,Y20:Y49) -> 0 | Z50: =SUM(Z20:Z49) -> 0
C52: S/N | D52: Activity | E52: Quantity (Insert only numeric values) | F52: Objective | G52: Expected output | H52: Achievement indicator | I52: Target group (Select from the drop-down) | J52: Timeline (Shade as applicable) | N52: Expected start date MM-DD-YYYY | O52: Expected due date MM-DD-YYYY | P52: Unit cost | Q52: Total cost (No input required) | R52: Implementation strategy (Select from the drop-down list) | S52: Resource mapping | Z52: Funding gap (No input required) | AA52: Remarks
S53: Government fund | V53: Development partner 1 | X53: Development partner 2
J54: Q1 | K54: Q2 | L54: Q3 | M54: Q4 | S54: State education budget | T54: UBEC matching grant | U54: Unconditional grants/Emergency funds | V54: Name | W54: Amount | X54: Name | Y54: Amount
C55: Priority initiative 3.2: Ensure transparent and effective financial management at state and LGA levels
C56: 3.2.1 | D56: Strengthen financial reporting systems at SUBEB level using digital tools | P56: 0 | Q56: =$E56*$P56 -> 0 | S56: 0 | T56: 0 | U56: 0 | W56: 0 | Y56: 0 | Z56: =Q56-SUM(S56:U56, W56,Y56) -> 0
C57: 3.2.2 | D57: Implement school grants and ensure SBMCs adopt financial accountability framework | P57: 0 | Q57: =$E57*$P57 -> 0 | S57: 0 | T57: 0 | U57: 0 | W57: 0 | Y57: 0 | Z57: =Q57-SUM(S57:U57, W57,Y57) -> 0
C58: 3.2.3 | P58: 0 | Q58: =$E58*$P58 -> 0 | S58: 0 | T58: 0 | U58: 0 | W58: 0 | Y58: 0 | Z58: =Q58-SUM(S58:U58, W58,Y58) -> 0
C59: 3.2.4 | P59: 0 | Q59: =$E59*$P59 -> 0 | S59: 0 | T59: 0 | U59: 0 | W59: 0 | Y59: 0 | Z59: =Q59-SUM(S59:U59, W59,Y59) -> 0
C60: 3.2.5 | P60: 0 | Q60: =$E60*$P60 -> 0 | S60: 0 | T60: 0 | U60: 0 | W60: 0 | Y60: 0 | Z60: =Q60-SUM(S60:U60, W60,Y60) -> 0
C61: 3.2.6 | P61: 0 | Q61: =$E61*$P61 -> 0 | S61: 0 | T61: 0 | U61: 0 | W61: 0 | Y61: 0 | Z61: =Q61-SUM(S61:U61, W61,Y61) -> 0
C62: 3.2.7 | P62: 0 | Q62: =$E62*$P62 -> 0 | S62: 0 | T62: 0 | U62: 0 | W62: 0 | Y62: 0 | Z62: =Q62-SUM(S62:U62, W62,Y62) -> 0
C63: 3.2.8 | P63: 0 | Q63: =$E63*$P63 -> 0 | S63: 0 | T63: 0 | U63: 0 | W63: 0 | Y63: 0 | Z63: =Q63-SUM(S63:U63, W63,Y63) -> 0
C64: 3.2.9 | P64: 0 | Q64: =$E64*$P64 -> 0 | S64: 0 | T64: 0 | U64: 0 | W64: 0 | Y64: 0 | Z64: =Q64-SUM(S64:U64, W64,Y64) -> 0
C65: 3.2.10 | P65: 0 | Q65: =$E65*$P65 -> 0 | S65: 0 | T65: 0 | U65: 0 | W65: 0 | Y65: 0 | Z65: =Q65-SUM(S65:U65, W65,Y65) -> 0
C66: 3.2.11 | P66: 0 | Q66: =$E66*$P66 -> 0 | S66: 0 | T66: 0 | U66: 0 | W66: 0 | Y66: 0 | Z66: =Q66-SUM(S66:U66, W66,Y66) -> 0
C67: 3.2.12 | P67: 0 | Q67: =$E67*$P67 -> 0 | S67: 0 | T67: 0 | U67: 0 | W67: 0 | Y67: 0 | Z67: =Q67-SUM(S67:U67, W67,Y67) -> 0
C68: 3.2.13 | P68: 0 | Q68: =$E68*$P68 -> 0 | S68: 0 | T68: 0 | U68: 0 | W68: 0 | Y68: 0 | Z68: =Q68-SUM(S68:U68, W68,Y68) -> 0
C69: 3.2.14 | P69: 0 | Q69: =$E69*$P69 -> 0 | S69: 0 | T69: 0 | U69: 0 | W69: 0 | Y69: 0 | Z69: =Q69-SUM(S69:U69, W69,Y69) -> 0
... C85: 3.2.30 | P85: 0 | Q85: =$E85*$P85 -> 0 | S85: 0 | T85: 0 | U85: 0 | W85: 0 | Y85: 0 | Z85: =Q85-SUM(S85:U85, W85,Y85) -> 0
C86: TOTAL | Q86: =SUM(Q56:Q85) -> 0 | S86: =SUM(S56:S85) -> 0 | T86: =SUM(T56:T85) -> 0 | U86: =SUM(U56:U85) -> 0 | V86: =SUM(W56:W85,Y56:Y85) -> 0 | Z86: =SUM(Z56:Z85) -> 0
C88: S/N | D88: Activity | E88: Quantity (Insert only numeric values) | F88: Objective | G88: Expected output | H88: Achievement indicator | I88: Target group (Select from the drop-down) | J88: Timeline (Shade as applicable) | N88: Expected start date MM-DD-YYYY | O88: Expected due date MM-DD-YYYY | P88: Unit cost | Q88: Total cost (No input required) | R88: Implementation strategy (Select from the drop-down list) | S88: Resource mapping | Z88: Funding gap (No input required) | AA88: Remarks
S89: Government fund | V89: Development partner 1 | X89: Development partner 2
J90: Q1 | K90: Q2 | L90: Q3 | M90: Q4 | S90: State education budget | T90: UBEC matching grant | U90: Unconditional grants/Emergency funds | V90: Name | W90: Amount | X90: Name | Y90: Amount
C91: Priority initiative 3.3: Strengthen SUBEB’s brand reputation with stakeholders through strategic engagements, media, and other activities
C92: 3.3.1 | D92: Disseminate annual progress report through daily newspapers | P92: 0 | Q92: =E92*P92 -> 0 | S92: 0 | T92: 0 | U92: 0 | W92: 0 | Y92: 0 | Z92: =Q92-SUM(S92:U92, W92,Y92) -> 0
C93: 3.3.2 | P93: 0 | Q93: =E93*P93 -> 0 | S93: 0 | T93: 0 | U93: 0 | W93: 0 | Y93: 0 | Z93: =Q93-SUM(S93:U93, W93,Y93) -> 0
C94: 3.3.3 | P94: 0 | Q94: =E94*P94 -> 0 | S94: 0 | T94: 0 | U94: 0 | W94: 0 | Y94: 0 | Z94: =Q94-SUM(S94:U94, W94,Y94) -> 0
C95: 3.3.4 | P95: 0 | Q95: =E95*P95 -> 0 | S95: 0 | T95: 0 | U95: 0 | W95: 0 | Y95: 0 | Z95: =Q95-SUM(S95:U95, W95,Y95) -> 0
C96: 3.3.5 | P96: 0 | Q96: =E96*P96 -> 0 | S96: 0 | T96: 0 | U96: 0 | W96: 0 | Y96: 0 | Z96: =Q96-SUM(S96:U96, W96,Y96) -> 0
C97: 3.3.6 | P97: 0 | Q97: =E97*P97 -> 0 | S97: 0 | T97: 0 | U97: 0 | W97: 0 | Y97: 0 | Z97: =Q97-SUM(S97:U97, W97,Y97) -> 0
C98: 3.3.7 | P98: 0 | Q98: =E98*P98 -> 0 | S98: 0 | T98: 0 | U98: 0 | W98: 0 | Y98: 0 | Z98: =Q98-SUM(S98:U98, W98,Y98) -> 0
C99: 3.3.8 | P99: 0 | Q99: =E99*P99 -> 0 | S99: 0 | T99: 0 | U99: 0 | W99: 0 | Y99: 0 | Z99: =Q99-SUM(S99:U99, W99,Y99) -> 0
C100: 3.3.9 | P100: 0 | Q100: =E100*P100 -> 0 | S100: 0 | T100: 0 | U100: 0 | W100: 0 | Y100: 0 | Z100: =Q100-SUM(S100:U100, W100,Y100) -> 0
C101: 3.3.10 | P101: 0 | Q101: =E101*P101 -> 0 | S101: 0 | T101: 0 | U101: 0 | W101: 0 | Y101: 0 | Z101: =Q101-SUM(S101:U101, W101,Y101) -> 0
C102: 3.3.11 | P102: 0 | Q102: =E102*P102 -> 0 | S102: 0 | T102: 0 | U102: 0 | W102: 0 | Y102: 0 | Z102: =Q102-SUM(S102:U102, W102,Y102) -> 0
C103: 3.3.12 | P103: 0 | Q103: =E103*P103 -> 0 | S103: 0 | T103: 0 | U103: 0 | W103: 0 | Y103: 0 | Z103: =Q103-SUM(S103:U103, W103,Y103) -> 0
C104: 3.3.13 | P104: 0 | Q104: =E104*P104 -> 0 | S104: 0 | T104: 0 | U104: 0 | W104: 0 | Y104: 0 | Z104: =Q104-SUM(S104:U104, W104,Y104) -> 0
... C121: 3.3.30 | P121: 0 | Q121: =E121*P121 -> 0 | S121: 0 | T121: 0 | U121: 0 | W121: 0 | Y121: 0 | Z121: =Q121-SUM(S121:U121, W121,Y121) -> 0
C122: TOTAL | Q122: =SUM(Q92:Q121) -> 0 | S122: =SUM(S92:S121) -> 0 | T122: =SUM(T92:T121) -> 0 | U122: =SUM(U92:U121) -> 0 | V122: =SUM(W92:W121,Y92:Y121) -> 0 | Z122: =SUM(Z92:Z121) -> 0
C124: S/N | D124: Activity | E124: Quantity (Insert only numeric values) | F124: Objective | G124: Expected output | H124: Achievement indicator | I124: Target group (Select from the drop-down) | J124: Timeline (Shade as applicable) | N124: Expected start date MM-DD-YYYY | O124: Expected due date MM-DD-YYYY | P124: Unit cost | Q124: Total cost (No input required) | R124: Implementation strategy (Select from the drop-down list) | S124: Resource mapping | Z124: Funding gap (No input required) | AA124: Remarks
S125: Government fund | V125: Development partner 1 | X125: Development partner 2
J126: Q1 | K126: Q2 | L126: Q3 | M126: Q4 | S126: State education budget | T126: UBEC matching grant | U126: Unconditional grants/Emergency funds | V126: Name | W126: Amount | X126: Name | Y126: Amount
C127: Priority initiative 3.4: Improve coordination and implementation of basic education programs with MoE, LGEAs, UBEC and other stakeholders
C128: 3.4.1 | D128: Conduct quarterly meeting with LGEAs | P128: 0 | Q128: =E128*P128 -> 0 | S128: 0 | T128: 0 | U128: 0 | W128: 0 | Y128: 0 | Z128: =Q128-SUM(S128:U128, W128,Y128) -> 0
C129: 3.4.2 | P129: 0 | Q129: =E129*P129 -> 0 | S129: 0 | T129: 0 | U129: 0 | W129: 0 | Y129: 0 | Z129: =Q129-SUM(S129:U129, W129,Y129) -> 0
C130: 3.4.3 | P130: 0 | Q130: =E130*P130 -> 0 | S130: 0 | T130: 0 | U130: 0 | W130: 0 | Y130: 0 | Z130: =Q130-SUM(S130:U130, W130,Y130) -> 0
C131: 3.4.4 | P131: 0 | Q131: =E131*P131 -> 0 | S131: 0 | T131: 0 | U131: 0 | W131: 0 | Y131: 0 | Z131: =Q131-SUM(S131:U131, W131,Y131) -> 0
C132: 3.4.5 | P132: 0 | Q132: =E132*P132 -> 0 | S132: 0 | T132: 0 | U132: 0 | W132: 0 | Y132: 0 | Z132: =Q132-SUM(S132:U132, W132,Y132) -> 0
C133: 3.4.6 | P133: 0 | Q133: =E133*P133 -> 0 | S133: 0 | T133: 0 | U133: 0 | W133: 0 | Y133: 0 | Z133: =Q133-SUM(S133:U133, W133,Y133) -> 0
C134: 3.4.7 | P134: 0 | Q134: =E134*P134 -> 0 | S134: 0 | T134: 0 | U134: 0 | W134: 0 | Y134: 0 | Z134: =Q134-SUM(S134:U134, W134,Y134) -> 0
C135: 3.4.8 | P135: 0 | Q135: =E135*P135 -> 0 | S135: 0 | T135: 0 | U135: 0 | W135: 0 | Y135: 0 | Z135: =Q135-SUM(S135:U135, W135,Y135) -> 0
C136: 3.4.9 | P136: 0 | Q136: =E136*P136 -> 0 | S136: 0 | T136: 0 | U136: 0 | W136: 0 | Y136: 0 | Z136: =Q136-SUM(S136:U136, W136,Y136) -> 0
C137: 3.4.10 | P137: 0 | Q137: =E137*P137 -> 0 | S137: 0 | T137: 0 | U137: 0 | W137: 0 | Y137: 0 | Z137: =Q137-SUM(S137:U137, W137,Y137) -> 0
C138: 3.4.11 | P138: 0 | Q138: =E138*P138 -> 0 | S138: 0 | T138: 0 | U138: 0 | W138: 0 | Y138: 0 | Z138: =Q138-SUM(S138:U138, W138,Y138) -> 0
C139: 3.4.12 | P139: 0 | Q139: =E139*P139 -> 0 | S139: 0 | T139: 0 | U139: 0 | W139: 0 | Y139: 0 | Z139: =Q139-SUM(S139:U139, W139,Y139) -> 0
C140: 3.4.13 | P140: 0 | Q140: =E140*P140 -> 0 | S140: 0 | T140: 0 | U140: 0 | W140: 0 | Y140: 0 | Z140: =Q140-SUM(S140:U140, W140,Y140) -> 0
... C157: 3.4.30 | P157: 0 | Q157: =E157*P157 -> 0 | S157: 0 | T157: 0 | U157: 0 | W157: 0 | Y157: 0 | Z157: =Q157-SUM(S157:U157, W157,Y157) -> 0
C158: TOTAL | Q158: =SUM(Q128:Q157) -> 0 | S158: =SUM(S128:S157) -> 0 | T158: =SUM(T128:T157) -> 0 | U158: =SUM(U128:U157) -> 0 | V158: =SUM(W128:W157,Y128:Y157) -> 0 | Z158: =SUM(Z128:Z157) -> 0
C160: S/N | D160: Activity | E160: Quantity (Insert only numeric values) | F160: Objective | G160: Expected output | H160: Achievement indicator | I160: Target group (Select from the drop-down) | J160: Timeline (Shade as applicable) | N160: Expected start date MM-DD-YYYY | O160: Expected due date MM-DD-YYYY | P160: Unit cost | Q160: Total cost (No input required) | R160: Implementation strategy (Select from the drop-down list) | S160: Resource mapping | Z160: Funding gap (No input required) | AA160: Remarks
S161: Government fund | V161: Development partner 1 | X161: Development partner 2
J162: Q1 | K162: Q2 | L162: Q3 | M162: Q4 | S162: State education budget | T162: UBEC matching grant | U162: Unconditional grants/Emergency funds | V162: Name | W162: Amount | X162: Name | Y162: Amount
C163: Enabler (Matching grant): Strengthen performance management, and routine monitoring and evaluation of Basic Education Programs (Planning & Education Management Information Systems)
C164: 1 | D164: Train EMIS officers on EMIS data entry and reporting and analysis | E164: 30 | F164: To Improve the Accuracy and Timeliness of Education Data Collection | G164: A strengthened, decentralized education data management system that produces timely, accurate, and reliable school-level data for informed decision-making, improved planning, and effective service delivery | H164: 100% Completion | I164: State level | N164: 45931 | O164: 46053 | P164: 102000 | Q164: =E164*P164 -> 3060000 | R164: E-payment/Cash transfer | S164: 0 | T164: 3060000 | U164: 0 | W164: 0 | Y164: 0 | Z164: =Q164-SUM(S164:U164, W164,Y164) -> 0
C165: 2 | D165: Conduct of Annual School Census across the State | E165: 1 | F165: To collect comprehensive, accurate, and up-to-date data on all aspects of basic education across the 23 Local Government Education Authorities (LGEAs), in order to inform evidence-based planning, budgeting, policy formulation, and education service delivery in line with UBEC and national EMIS standards. | G165: A comprehensive, accurate, and up-to-date education data system that enables evidence-based planning, equitable resource allocation, and effective monitoring of school performance across all public and non-public basic education institutions in Sample State. | H165: 100% coverage of all registered schools (e.g., ECCDE, Primary, and JSS) in the state | I165: State level | N165: 45931 | O165: 46053 | P165: 1.150757e+08 | Q165: =E165*P165 -> 1.150757e+08 | R165: E-payment/Cash transfer | S165: 0 | T165: 115075703 | U165: 0 | W165: 0 | Y165: 0 | Z165: =Q165-SUM(S165:U165, W165,Y165) -> 0.38
C166: 3 | D166: Procurement of all-in-one Hp 4GB DDR4 RAM, 512GB SSD Windows 11 Desktop Computers with Keyboard and Mouse | E166: 33 | F166: To provide PRS officers with functional digital tools for enhanced fieldwork. | G166: 33 Noall-in-one computers acquired | H166: 100% Completion | I166: State level | N166: 45931 | O166: 46053 | P166: 650000 | Q166: =E166*P166 -> 21450000 | R166: Request for quotation | S166: 0 | T166: 21450000 | U166: 0 | W166: 0 | Y166: 0 | Z166: =Q166-SUM(S166:U166, W166,Y166) -> 0 | AA166: The price covers taxes, delivery services and installation
C167: 4 | D167: Development of Basic Education Strategic Plan | E167: 1 | F167: To develope State Medium-Term Basic Education Strategic Plan (SMTBESP) | G167: A Strategic plan will be developed | H167: 100% Completion | I167: State level | N167: 45931 | O167: 46053 | P167: 2600000 | Q167: =E167*P167 -> 2600000 | R167: E-payment/Cash transfer | S167: 0 | T167: 2600000 | U167: 0 | W167: 0 | Y167: 0 | Z167: =Q167-SUM(S167:U167, W167,Y167) -> 0
C168: 5 | P168: 0 | Q168: =E168*P168 -> 0 | S168: 0 | T168: 0 | U168: 0 | W168: 0 | Y168: 0 | Z168: =Q168-SUM(S168:U168, W168,Y168) -> 0
C169: 6 | P169: 0 | Q169: =E169*P169 -> 0 | S169: 0 | T169: 0 | U169: 0 | W169: 0 | Y169: 0 | Z169: =Q169-SUM(S169:U169, W169,Y169) -> 0
C170: 7 | P170: 0 | Q170: =E170*P170 -> 0 | S170: 0 | T170: 0 | U170: 0 | W170: 0 | Y170: 0 | Z170: =Q170-SUM(S170:U170, W170,Y170) -> 0
C171: 8 | P171: 0 | Q171: =E171*P171 -> 0 | S171: 0 | T171: 0 | U171: 0 | W171: 0 | Y171: 0 | Z171: =Q171-SUM(S171:U171, W171,Y171) -> 0
C172: 9 | P172: 0 | Q172: =E172*P172 -> 0 | S172: 0 | T172: 0 | U172: 0 | W172: 0 | Y172: 0 | Z172: =Q172-SUM(S172:U172, W172,Y172) -> 0
...

Sheet Unit Cost Set-Up
B2: Review the list below. Add additional cost items or Adjust the unit cost where necessary. Please make all entries within the table
B3: State-specific Cost Assumptions
B4: Cost Items | C4: Unit Cost (₦)
B5: Construction of 2 classrooms with 2 playrooms, 4 toilets and interlocking | C5: 26521567
B30: •
B31: •
B32: •
B33: •
B34: •
B35: •
B36: •
B37: •
B38: •
B39: •
B40: •
B41: •
... B144: •

Sheet Activity costing 
B2: Pillar 1 | C2: Expand access to UBE especially for rural and undeserved populations
B3: Pillar 2 | C3: Enhance Quality of Teaching and Learning
B4: Pillar 3 | C4: Reform and Strengthen Basic Education Financing
B5: Pillar 4 | C5: Optimize institutional systems for quality service delivery
B6: Enablers
C9: Pillar 1 | D9: Expand access to UBE especially for rural and undeserved populations
C10: Activity | D10: Furniture | F10: Grand Total
C11: Input | D11: Quantity | E11: Frequency | F11: Unit cost | G11: Total
C12: Procurement of teacher furniture | D12: 50 | E12: 1 | G12: =PRODUCT(D12:F12) -> 50
F13: =VLOOKUP(C13,#REF!, 2, FALSE) -> #REF! | G13: =PRODUCT(D13:F13) -> #REF!
F14: =VLOOKUP(C14,#REF!, 2, FALSE) -> #REF! | G14: =PRODUCT(D14:F14) -> #REF!
F15: =VLOOKUP(C15,#REF!, 2, FALSE) -> #REF! | G15: =PRODUCT(D15:F15) -> #REF!
F16: =VLOOKUP(C16,#REF!, 2, FALSE) -> #REF! | G16: =PRODUCT(D16:F16) -> #REF!
G17: =PRODUCT(D17:F17) -> 0
C22: Activity | D22: ='Pillar 1 - Access'!E36 -> 0 | F22: Grand Total | G22: =SUM(G24:G32) -> #REF!
C23: Input | D23: Quantity | E23: Frequency | F23: Unit cost | G23: Total
F24: =VLOOKUP(C24,#REF!, 2, FALSE) -> #REF! | G24: =PRODUCT(D24:F24) -> #REF!
F25: =VLOOKUP(C25,#REF!, 2, FALSE) -> #REF! | G25: =PRODUCT(D25:F25) -> #REF!
F26: =VLOOKUP(C26,#REF!, 2, FALSE) -> #REF! | G26: =PRODUCT(D26:F26) -> #REF!
F27: =VLOOKUP(C27,#REF!, 2, FALSE) -> #REF! | G27: =PRODUCT(D27:F27) -> #REF!
F28: =VLOOKUP(C28,#REF!, 2, FALSE) -> #REF! | G28: =PRODUCT(D28:F28) -> #REF!
F29: =VLOOKUP(C29,#REF!, 2, FALSE) -> #REF! | G29: =PRODUCT(D29:F29) -> #REF!
F30: =VLOOKUP(C30,#REF!, 2, FALSE) -> #REF! | G30: =PRODUCT(D30:F30) -> #REF!
F31: =VLOOKUP(C31,#REF!, 2, FALSE) -> #REF! | G31: =PRODUCT(D31:F31) -> #REF!
F32: =VLOOKUP(C32,#REF!, 2, FALSE) -> #REF! | G32: =PRODUCT(D32:F32) -> #REF!
C34: Activity | D34: 0 | F34: Grand Total
C35: Input | D35: Quantity | E35: Frequency | F35: Unit cost | G35: Total
C45: Activity | D45: 0 | F45: Grand Total
C46: Input | D46: Quantity | E46: Frequency | F46: Unit cost | G46: Total
C57: Activity | D57: 0 | F57: Grand Total
C58: Input | D58: Quantity | E58: Frequency | F58: Unit cost | G58: Total
C69: Activity | D69: 0 | F69: Grand Total
C70: Input | D70: Quantity | E70: Frequency | F70: Unit cost | G70: Total
C80: Activity | D80: 0 | F80: Grand Total
C81: Input | D81: Quantity | E81: Frequency | F81: Unit cost | G81: Total
C92: Activity | D92: 0 | F92: Grand Total
C93: Input | D93: Quantity | E93: Frequency | F93: Unit cost | G93: Total
C104: Activity | D104: 0 | F104: Grand Total
C105: Input | D105: Quantity | E105: Frequency | F105: Unit cost | G105: Total
C116: Activity | D116: Activity | F116: Grand Total
C117: Input | D117: Quantity | E117: Frequency | F117: Unit cost | G117: Total
C127: Activity | D127: 0 | F127: Grand Total
C128: Input | D128: Quantity | E128: Frequency | F128: Unit cost | G128: Total
C139: Activity | D139: 0 | F139: Grand Total
C140: Input | D140: Quantity | E140: Frequency | F140: Unit cost | G140: Total
C151: Activity | D151: 0 | F151: Grand Total
C152: Input | D152: Quantity | E152: Frequency | F152: Unit cost | G152: Total
C162: Activity | D162: 0 | F162: Grand Total
C163: Input | D163: Quantity | E163: Frequency | F163: Unit cost | G163: Total

Sheet Total budget summary
B1: Total Available UBE Funds
B2: Total Matching Grant Accessed | C2: ='Welcome Page'!C8 -> 7.1092852e+09
B3: Total Matching Grant Allocated in Action Plan | C3: =SUM(D38:D46) -> 7.1092852e+09
B4: Total State Budget for BEAP activities (excludes matching grant) | C4: ='Pillar 1 - Access'!S201+'Pillar 2 - Quality'!O227+'Pillar 3 - Systems Optimization'!S232 -> 989400000
B5: Total Donor funding for planned BEAP activities | C5: ='Pillar 1 - Access'!V201+'Pillar 2 - Quality'!R227+'Pillar 3 - Systems Optimization'!V232 -> 0
B6: Total Unconditional Grant/ Emergency funds for planned BEAP activities | C6: ='Pillar 1 - Access'!U201+'Pillar 2 - Quality'!Q227+'Pillar 3 - Systems Optimization'!U232 -> 230000000
B7: Total | C7: =SUM(C3:D6) -> 8.3286852e+09
B9: Summary of Funds Allocated by Pillar
B10: Pillar | C10: Total cost | D10: Percentage of total budget
B11: Pillar 1: Expand access to UBE esp for rural and undeserved populations | C11: ='Pillar 1 - Access'!Q201 -> 5.1063128e+09 | D11: =IFERROR(C11/C7,"") -> 0.61309952
B12: ='Pillar 1 - Access'!C17 -> Priority initiative 1.1: Provide safe and adequate infrastructure for learning environments (Hope-EDU DLI) | C12: ='Pillar 1 - Access'!O28 -> 4.6086629e+09
B13: ='Pillar 1 - Access'!C33 -> Priority initiative 1.2: Expand enrollment of out-of-school children into the formal education system (Hope-EDU DLI) | C13: ='Pillar 1 - Access'!Q66 -> 0
B14: ='Pillar 1 - Access'!C71 -> Priority initiative 1.3 (Matching grant): Improve retention with incentives such as School Based Management Committee (SMBC) initiatives | C14: ='Pillar 1 - Access'!Q123 -> 3.5546426e+08
B15: ='Pillar 1 - Access'!C128 -> Enabler (Matching grant): Supervision and Project monitoring of ongoing infrastructure activities | C15: ='Pillar 1 - Access'!Q159 -> 1.421857e+08
B16: ='Pillar 1 - Access'!C166 -> Enabler: Partnerships and cross-sector collaboration to expand access to basic education | C16: ='Pillar 1 - Access'!P197 -> 0
B18: Pillar 2: Enhance quality of teaching and learning | C18: ='Pillar 2 - Quality'!N227 -> 2.6027789e+09 | D18: =IFERROR(C18/C7,"") -> 0.31250778
B19: ='Pillar 2 - Quality'!C20 -> Priority initiative 2.1 (Matching grant): Ensure implementation of revised basic education curriculum across schools | C19: ='Pillar 2 - Quality'!Q51 -> 1.421857e+08
B20: ='Pillar 2 - Quality'!C56 -> Priority initiative 2.2: Provision of adequate Teaching and Learning Materials (TLMs) for schools (Hope-EDU DLI) | C20: ='Pillar 2 - Quality'!Q87 -> 722400000
B21: ='Pillar 2 - Quality'!C93 -> Priority initiative 2.3: Teacher/ education managers training and capacity building (Hope-EDU DLI) | C21: ='Pillar 2 - Quality'!Q124 -> 0
B22: ='Pillar 2 - Quality'!C204 -> Matching Grant Intervention: Sports Development | C22: ='Pillar 2 - Quality'!I209 -> 1.421857e+08
B23: ='Pillar 2 - Quality'!C214 -> Matching Grant Intervention: Green School and Climate Change and Safeguards | C23: ='Pillar 2 - Quality'!I224 -> 1.421857e+08
B24: ='Pillar 2 - Quality'!C132 -> Enabler (Matching grant): Quality Assurance monitoring | C24: ='Pillar 2 - Quality'!P163 -> 1.0895755e+08
B25: ='Pillar 2 - Quality'!C168 -> Enabler (Matching grant): Leveraging digitalization to improve the quality of basic education (ICT and Data Platform) | C25: ='Pillar 2 - Quality'!Q199 -> 3.5546426e+08
B27: Pillar 3: Optimize institutional systemns for quality service delivery | C27: ='Pillar 3 - Systems Optimization'!Q232 -> 3.8869242e+08 | D27: =IFERROR(C27/C7,"") -> 0.046669121
B28: ='Pillar 3 - Systems Optimization'!C19 -> Priority initiative 3.1: Optimize organizational structure, guidelines, and personnel capacity to effectively deliver on mandate and impact | C28: ='Pillar 3 - Systems Optimization'!Q50 -> 0
B29: ='Pillar 3 - Systems Optimization'!C55 -> Priority initiative 3.2: Ensure transparent and effective financial management at state and LGA levels | C29: ='Pillar 3 - Systems Optimization'!Q86 -> 0
B30: ='Pillar 3 - Systems Optimization'!C91 -> Priority initiative 3.3: Strengthen SUBEB’s brand reputation with stakeholders through strategic engagements, media, and other activities | C30: ='Pillar 3 - Systems Optimization'!Q122 -> 0
B31: ='Pillar 3 - Systems Optimization'!C127 -> Priority initiative 3.4: Improve coordination and implementation of basic education programs with MoE, LGEAs, UBEC and other stakeholders | C31: ='Pillar 3 - Systems Optimization'!Q158 -> 0
B32: ='Pillar 3 - Systems Optimization'!C163 -> Enabler (Matching grant): Strengthen performance management, and routine monitoring and evaluation of Basic Education Programs (Planning & Education Management Information Systems) | C32: ='Pillar 3 - Systems Optimization'!Q194 -> 1.421857e+08
B33: ='Pillar 3 - Systems Optimization'!C199 -> Enabler: Instituting a framework for quality assurance to improve access to basic education | C33: ='Pillar 3 - Systems Optimization'!P230 -> 2.4650671e+08
B36: Summary of Funds Allocated Across UBEC Matching Grant Utilization Domains (per guidelines)
B37: Description | C37: Percentage | D37: Amount
B38: Infastructructure projects and TLMs | C38: =(IFERROR(D38/$D$47,0)) -> 0.75 | D38: ='Infrastructure Projects'!L9 -> 5.3319639e+09
B39: Purchase and distribution of curriculum | C39: =(IFERROR(D39/$D$47,0)) -> 0.02 | D39: ='Pillar 2 - Quality'!Q51 -> 1.421857e+08
B40: ICT and Data Platform | C40: =(IFERROR(D40/$D$47,0)) -> 0.05 | D40: ='Pillar 2 - Quality'!Q199 -> 3.5546426e+08
B41: SBMC | C41: =(IFERROR(D41/$D$47,0)) -> 0.05 | D41: ='Pillar 1 - Access'!Q123 -> 3.5546426e+08
B42: Planning & Education Management Information systems | C42: =(IFERROR(D42/$D$47,0)) -> 0.02 | D42: ='Pillar 3 - Systems Optimization'!Q194 -> 1.421857e+08
B43: Greening Schools Climate Change and Safeguards | C43: =(IFERROR(D43/$D$47,0)) -> 0.02 | D43: ='Pillar 2 - Quality'!I224 -> 1.421857e+08
B44: Sports Development | C44: =(IFERROR(D44/$D$47,0)) -> 0.02 | D44: ='Pillar 2 - Quality'!I209 -> 1.421857e+08
B45: Quality Assurance Monitoring | C45: =(IFERROR(D45/$D$47,0)) -> 0.05 | D45: =SUM(C24,C33) -> 3.5546426e+08
B46: Supervision and Project Monitoring | C46: =(IFERROR(D46/$D$47,0)) -> 0.02 | D46: =SUM(C15) -> 1.421857e+08
B47: Total | C47: =SUM(C38:C46) -> 1 | D47: =SUM(D38:D46) -> 7.1092852e+09
B68: Infastructure deliverables summary | C68: Expected outcome | G68: Implementation strategy
B69: New construction | C69: ECCDE | D69: Primary | E69: JSS | G69: NCB
B70: No of new classrooms | C70: =SUMIF('Infrastructure Projects'!G18:G538, "ECCDE", 'Infrastructure Projects'!N18:N538) -> 3 | D70: =SUMIF('Infrastructure Projects'!G18:G538, "Primary", 'Infrastructure Projects'!N18:N538) -> 0 | E70: =SUMIF('Infrastructure Projects'!G18:G538, "JSS", 'Infrastructure Projects'!N18:N538) -> 3 | G70: Request for quotation
B71: No of new playrooms/Laboratories | C71: =SUMIF('Infrastructure Projects'!G18:G538, "ECCDE", 'Infrastructure Projects'!O18:O538) -> 0 | D71: =SUMIF('Infrastructure Projects'!G18:G538, "Primary", 'Infrastructure Projects'!O18:O538) -> 0 | E71: =SUMIF('Infrastructure Projects'!G18:G538, "JSS", 'Infrastructure Projects'!O18:O538) -> 0 | G71: Market survey
B72: No of new library | C72: =SUMIF('Infrastructure Projects'!G18:G538, "ECCDE", 'Infrastructure Projects'!P18:P538) -> 0 | D72: =SUMIF('Infrastructure Projects'!G18:G538, "Primary", 'Infrastructure Projects'!P18:P538) -> 0 | E72: =SUMIF('Infrastructure Projects'!G18:G538, "JSS", 'Infrastructure Projects'!P18:P538) -> 0 | G72: Single source/Direct contracting
B73: No of toilets | C73: =SUMIF('Infrastructure Projects'!G18:G538, "ECCDE", 'Infrastructure Projects'!Q18:Q538) -> 18 | D73: =SUMIF('Infrastructure Projects'!G18:G538, "Primary", 'Infrastructure Projects'!Q18:Q538) -> 12 | E73: =SUMIF('Infrastructure Projects'!G18:G538, "JSS", 'Infrastructure Projects'!Q18:Q538) -> 18 | G73: Prequalification
B74: No of new offices/stores | C74: =SUMIF('Infrastructure Projects'!G18:G538, "ECCDE", 'Infrastructure Projects'!R18:R538) -> 2 | D74: =SUMIF('Infrastructure Projects'!G18:G538, "Primary", 'Infrastructure Projects'!R18:R538) -> 0 | E74: =SUMIF('Infrastructure Projects'!G18:G538, "JSS", 'Infrastructure Projects'!R18:R538) -> 2 | G74: Quality and cost based
B75: No of fences constructed | C75: =COUNTIF('Infrastructure Projects'!G544:G644, "ECCDE") -> 3 | D75: =COUNTIF('Infrastructure Projects'!G544:G644, "Primary") -> 2 | E75: =COUNTIF('Infrastructure Projects'!G544:G644, "JSS") -> 3 | G75: Consultant Qualification
G76: E-payment/Cash transfer
B77: Renovation | C77: ECCDE | D77: Primary | E77: JSS | G77: Credit School account
B78: No of classrooms renovated | C78: =SUMIF('Infrastructure Projects'!G652:G952, "ECCDE", 'Infrastructure Projects'!O652:O952) -> 12 | D78: =SUMIF('Infrastructure Projects'!G652:G952, "Primary", 'Infrastructure Projects'!O652:O952) -> 37 | E78: =SUMIF('Infrastructure Projects'!G652:G952, "JSS", 'Infrastructure Projects'!O652:O952) -> 30 | G78: Credit SBMC school account
B79: No of playrooms/labs renovated | C79: =SUMIF('Infrastructure Projects'!G652:G952, "ECCDE", 'Infrastructure Projects'!P652:P952) -> 0 | D79: =SUMIF('Infrastructure Projects'!G652:G952, "Primary", 'Infrastructure Projects'!P652:P952) -> 1 | E79: =SUMIF('Infrastructure Projects'!G652:G952, "JSS", 'Infrastructure Projects'!P652:P952) -> 2 | G79: Credit staff concern account
B80: No of library renovated | C80: =SUMIF('Infrastructure Projects'!G652:G952, "ECCDE", 'Infrastructure Projects'!Q652:Q952) -> 0 | D80: =SUMIF('Infrastructure Projects'!G652:G952, "Primary", 'Infrastructure Projects'!Q652:Q952) -> 0 | E80: =SUMIF('Infrastructure Projects'!G652:G952, "JSS", 'Infrastructure Projects'!Q652:Q952) -> 1 | G80: Direct payment to vendor
B81: No of toilets renovated | C81: =SUMIF('Infrastructure Projects'!G652:G952, "ECCDE", 'Infrastructure Projects'!R652:R952) -> 6 | D81: =SUMIF('Infrastructure Projects'!G652:G952, "Primary", 'Infrastructure Projects'!R652:R952) -> 14 | E81: =SUMIF('Infrastructure Projects'!G652:G952, "JSS", 'Infrastructure Projects'!R652:R952) -> 4
B82: No of offices/stores renovated | C82: =SUMIF('Infrastructure Projects'!G652:G952, "ECCDE", 'Infrastructure Projects'!S652:S952) -> 4 | D82: =SUMIF('Infrastructure Projects'!G652:G952, "Primary", 'Infrastructure Projects'!S652:S952) -> 12 | E82: =SUMIF('Infrastructure Projects'!G652:G952, "JSS", 'Infrastructure Projects'!S652:S952) -> 10
B83: No of furniture procured | C83: =SUMIF('Infrastructure Projects'!G961:G1261, "ECCDE", 'Infrastructure Projects'!F961:F1261) -> 60 | D83: =SUMIF('Infrastructure Projects'!G961:G1261, "Primary", 'Infrastructure Projects'!F961:F1261) -> 740 | E83: =SUMIF('Infrastructure Projects'!G961:G1261, "JSS", 'Infrastructure Projects'!F961:F1261) -> 2315
B84: No of boreholes constructed | C84: =SUMIF('Infrastructure Projects'!G1270:G1370, "ECCDE", 'Infrastructure Projects'!F1270:F1370) -> 4 | D84: =SUMIF('Infrastructure Projects'!G1270:G1370, "Primary", 'Infrastructure Projects'!F1270:F1370) -> 2 | E84: =SUMIF('Infrastructure Projects'!G1270:G1370, "JSS", 'Infrastructure Projects'!F1270:F1370) -> 4
B85: TLMs | C85: =SUMIF('Infrastructure Projects'!G1425:G1725, "ECCDE", 'Infrastructure Projects'!F1425:F1725) -> 0 | D85: =SUMIF('Infrastructure Projects'!G1425:G1725, "Primary", 'Infrastructure Projects'!F1425:F1725) -> 21955 | E85: =SUMIF('Infrastructure Projects'!G1425:G1725, "JSS", 'Infrastructure Projects'!F1425:F1725) -> 0
B89: Pillar 1 | C89: =C11 -> 5.1063128e+09 | D89: =C89/$C$92 -> 0.63058149
B90: Pillar 2 | C90: =C18 -> 2.6027789e+09 | D90: =C90/$C$92 -> 0.32141866
B91: Pillar 3 | C91: =C27 -> 3.8869242e+08 | D91: =C91/$C$92 -> 0.047999849
B92: Total | C92: =SUM(C89:C91) -> 8.0977842e+09 | D92: =C92/$C$92 -> 1
B94: Furniture procured
B95: ECCDE | C95: =C83 -> 60
B96: Primary | C96: =D83 -> 740
B97: JSS | C97: =E83 -> 2315
B99: Boreholes
B100: ECCDE | C100: =C84 -> 4
B101: Primary | C101: =D84 -> 2
B102: JSS | C102: =E84 -> 4
B105: TLMs
B106: ECCDE | C106: =C85 -> 0
B107: Primary | C107: =D85 -> 21955
B108: JSS | C108: =E85 -> 0

Sheet HOPE-DLI 
B2: Pillars | C2: Disbursement Linked Indicators (DLIs) | D2: DLIs Expected Results | E2: Sample activities
B3: Expand Access to UBE | C3: DLI 4: Number of new primary classrooms created through community participation | D3: Government-community agreements signed to create new classrooms | E3: Construction of 2 Storey building blocks of 4 Classrooms, 3 Offices, 1 Library/Computer lab, Store, Playroom and 10 Water Closet
D4: 13,000 new classrooms created
C5: DLI 5: Number of out-of-school children who complete NFBE program | D5: 10,000 NFLCs have Management Committee, Teachers, and TLMs | E5: Implement open school activities in nomadic and high density IDP camps across 3 LGAs
D6: 1,500,000 out-of-school children complete NFBE program
B7: Enhance Quality of Teaching and Learning | C7: DLI 1: Number of schools with sufficient TLMs for literacy and numeracy, by grade | D7: TLMs quality-assured and needs-estimated, and track-trace system approved | E7: Conduct needs assessment for textbooks and structured pedagogy materials
D8: Primary schools have sufficient TLMs for literacy and numeracy | E8: Distribute updated text books for core subjects across 50 schools in 10 LGAs
C9: DLI 2: Number of primary teachers with improved structured pedagogy practices (SPP) | D9: SPP training packages approved | E9: 1) Provide training for 1,000 teachers and mentors on structured pedagogy 2) Establish a mentorship program for 1,000 trained teachers
D10: All primary teachers and mentors enabled to improve SPP
D11: All Grades 1-3 teachers regularly mentored on SPP
D12: All primary teachers regularly mentored on SPP
D13: Number of primary teachers with improved SPP
C14: DLI 3: Percentage of children proficient in literacy and numeracy | D14: Learning evaluation mechanisms for Grades 1-2 literacy and numeracy approved | E14: 1) Establish baseline proficiency levels for literacy and numeracy across basic education 2) Conduct periodic student learning evaluations across 21 LGEA
D15: Number of LGEAs acting on early learning evaluations
D16: Increased percentage of children proficient in literacy and numeracy
B17: Reform and Strengthen Basic Education Financing | C17: DLI 7: Percentage of public primary schools using annual school grant (ASG) | D17: ASG amount and management regulations approved | E17: Implement school grants and ensure SBMCs adopt financial accountability framework
D18: 70 percent of public primary schools use ASG
D19: 90 percent of public primary schools use ASG
B20: Enabler: Strengthen performance management, monitoring and evaluation | C20: DLI 8: Percentage of schools included in current-year Annual School Census (ASC) Report | D20: State digital ASC system operational | E20: Train education officers on EMIS data entry and analysis
D21: 85% of schools included in current-year State ASC Report | E21: Implement a state-level digital education dashboard for decision-making
D22: 95% of schools included in current-year State ASC Report | E22: Track conduct of annual school census across 21 LGEAs
